Workbook
Name SegmentaciónDeDatos_FACTOR_DE_RIESGO_PROGRAMA: #N/A
Name SegmentaciónDeDatos_RESPONSABLES: #N/A

Sheet DASHBOARD
A1: Año | C1: Proyecto | H1: Líder HSEQ del proyecto: | O1: Centro de trabajo ( Indicar: nombre cliente, # contrato, objeto de contrato)
A2: 2026 | C2: ESSA- OBRAS | H2: KELLY CALLE | O2: ESSA EPM Servicios de mantenimiento de líneas de transmisión de energía CW261422
A3: Se proyectan capacitaciones asociadas a gestion ambiental relacionando: riesgo quimico, biológico, las demás relacionadas al cuidado del medio ambiente serán proyectadas por la Dir. Ambiental desde los programas de gestión. | O3: Fecha inicio actividades operativas en el periodo | U3: 46035
A6: ANALISIS DEL DESARROLLO DEL PLAN ANUAL DE CAPACITACION Y REQUERIMIENTOS PARA TRATAMIENTO A DESVIACIONES ( trimestral):
A8: Trimestre 1
A10: Trimestre 2
A12: Trimestre 3
A14: Trimestre 4
O19: ENE | P19: FEB | Q19: MAR | R19: ABR | S19: MAY | T19: JUN | U19: JUL | V19: AGO | W19: SEP | X19: OCT | Y19: NOV | Z19: DIC | AA19: TOTAL | AB19: META
N20: PLANEADAS | O20: =COUNTIF('PLAN CAP'!N5:N53,"=1") -> 1 | P20: =COUNTIF('PLAN CAP'!O5:O53,"=1") -> 5 | Q20: =COUNTIF('PLAN CAP'!P5:P53,"=1") -> 5 | R20: =COUNTIF('PLAN CAP'!Q5:Q53,"=1") -> 5 | S20: =COUNTIF('PLAN CAP'!R5:R53,"=1") -> 5 | T20: =COUNTIF('PLAN CAP'!S5:S53,"=1") -> 5 | U20: =COUNTIF('PLAN CAP'!T5:T53,"=1") -> 5 | V20: =COUNTIF('PLAN CAP'!U5:U53,"=1") -> 5 | ... Z20: =COUNTIF('PLAN CAP'!Y5:Y53,"=1") -> 1 | AA20: =SUM(O20:Z20) -> 49
N21: EJECUTADAS | O21: =COUNTIF('PLAN CAP'!N5:N53,"=2") -> 0 | P21: =COUNTIF('PLAN CAP'!O5:O53,"=2") -> 0 | Q21: =COUNTIF('PLAN CAP'!P5:P53,"=2") -> 0 | R21: =COUNTIF('PLAN CAP'!Q5:Q53,"=2") -> 0 | S21: =COUNTIF('PLAN CAP'!R5:R53,"=2") -> 0 | T21: =COUNTIF('PLAN CAP'!S5:S53,"=2") -> 0 | U21: =COUNTIF('PLAN CAP'!T5:T53,"=2") -> 0 | V21: =COUNTIF('PLAN CAP'!U5:U53,"=2") -> 0 | ... Z21: =COUNTIF('PLAN CAP'!Y5:Y53,"=2") -> 0 | AA21: =SUM(O21:Z21) -> 0
N22: CAN / REP | O22: =COUNTIF('PLAN CAP'!N5:N53,"=0") -> 0 | P22: =COUNTIF('PLAN CAP'!O5:O53,"=0") -> 0 | Q22: =COUNTIF('PLAN CAP'!P5:P53,"=0") -> 0 | R22: =COUNTIF('PLAN CAP'!Q5:Q53,"=0") -> 0 | S22: =COUNTIF('PLAN CAP'!R5:R53,"=0") -> 0 | T22: =COUNTIF('PLAN CAP'!S5:S53,"=0") -> 0 | U22: =COUNTIF('PLAN CAP'!T5:T53,"=0") -> 0 | V22: =COUNTIF('PLAN CAP'!U5:U53,"=0") -> 0 | ... AA22: =COUNTIF('PLAN CAP'!Z5:Z53,"=0") -> 49
AB23: 1
N24: CUMPLIMIENTO | O24: =IF((O20+O21+O22)=0,"100%",(O21/(O20+O21+O22))) -> 0 | P24: =IF((P20+P21+P22)=0,"100%",(P21/(P20+P21+P22))) -> 0 | Q24: =IF((Q20+Q21+Q22)=0,"100%",(Q21/(Q20+Q21+Q22))) -> 0 | R24: =IF((R20+R21+R22)=0,"100%",(R21/(R20+R21+R22))) -> 0 | S24: =IF((S20+S21+S22)=0,"100%",(S21/(S20+S21+S22))) -> 0 | T24: =IF((T20+T21+T22)=0,"100%",(T21/(T20+T21+T22))) -> 0 | U24: =IF((U20+U21+U22)=0,"100%",(U21/(U20+U21+U22))) -> 0 | V24: =IF((V20+V21+V22)=0,"100%",(V21/(V20+V21+V22))) -> 0 | ... AA24: =IF((AA20+AA21+AA22)=0,"100%",(AA21/(AA20+AA21+AA22))) -> 0 | AB24: =AB23-AA24 -> 1

Sheet planeado inicial
C1: ENE | D1: FEB | E1: MAR | F1: ABR | G1: MAY | H1: JUN | I1: JUL | J1: AGO | K1: SEP | L1: OCT | M1: NOV | N1: DIC | O1: TOTAL | P1: META
B2: PLANEADAS | C2: 1 | D2: 5 | E2: 5 | F2: 5 | G2: 5 | H2: 5 | I2: 5 | J2: 5 | K2: 5 | L2: 5 | M2: 4 | N2: 1 | O2: 51
B3: EJECUTADAS | C3: 0 | D3: 0 | E3: 0 | F3: 0 | G3: 0 | H3: 0 | I3: 0 | J3: 0 | K3: 0 | L3: 0 | M3: 0 | N3: 0 | O3: 0
B4: CAN / REP | C4: 0 | D4: 0 | E4: 0 | F4: 0 | G4: 0 | H4: 0 | I4: 0 | J4: 0 | K4: 0 | L4: 0 | M4: 0 | N4: 0 | O4: 51
P5: 1
B6: CUMPLIMIENTO | C6: 0 | D6: 0 | E6: 0 | F6: 0 | G6: 0 | H6: 0 | I6: 0 | J6: 0 | K6: 0 | L6: 0 | M6: 0 | N6: 0 | O6: 0 | P6: 1

Sheet PLAN CAP
C1: PLAN DE CAPACITACION SG-SST | AA1: Código: FT-HSEQ-120
AA2: Versión: 06
AA3: Fecha de aprobación: 06 enero de 2026
A4: OBJETIVO DE LA ACTIVIDAD | B4: FACTOR DE RIESGO/PROGRAMA | C4: TEMA DE INTERVENCIÓN: definir que se quiere transmitir, antecedentes del riesgo o del evento | D4: Origen /necesidad | E4: OBJETIVO | F4: OBJETIVOS ESPECÍFICOS | G4: Intensidad horaria por trabajador | H4: METODOLOGIA: plantear la metodologia a utilizar en la actividad | I4: EVALUACIÓN: definir si se realizara evaluacion, metodo de evaluación. | J4: Evidencia de la formaciòn | K4: POBLACION OBJETO | L4: CENTRO DE TRABAJO | M4: RESPONSABLES | N4: ENE | O4: FEB | P4: MAR | Q4: ABR | R4: MAY | S4: JUN | T4: JUL | U4: AGO | V4: SEP | W4: OCT | X4: NOV | Y4: DIC | Z4: % COMPLETADO | AA4: OBSERVACIONES Y SEGUIMIENTO
A5: PROCESO DE INDUCCION / REINDUCCIÒN | B5: INDUCCION / REINDUCCION SGI | C5: Inducción/reinducciòn ( SD SAS) | D5: REQUISITO LEGAL | E5: Divulgar al personal nuevo y antiguo los siguientes temas: general de la empresa, calidad, seguridad y salud en el trabajo, gestión Ambiental, de acuerdo al cargo y otros temas. (Cada vez que ingresa personal) | F5: Conocer las políticas, objetivos y lineamientos del Sistema de Gestión de Seguridad y Salud en el Trabajo (SG‑SST) y su aplicación en SD SAS. Identificar los riesgos generales presentes en la empresa, incluyendo riesgos físicos, mecánicos, locativos, químicos, biológicos, biomecánicos, psicosociales y viales. Reconocer los riesgos eléctricos asociados a sus funciones y las medidas de prevención y control establecidas. Identificar los riesgos específicos en actividades de poda, tala e intervención de vegetación, especialmente en cercanías a redes eléctricas. Aplicar las acciones preventivas del SG‑SST, tales como reporte de condiciones inseguras, cumplimiento de procedimientos y uso adecuado del EPP. Reconocer sus derechos, deberes y responsabilidades frente a la Seguridad y Salud en el Trabajo. Identificar y aplicar los procedimientos de trabajo seguro relacionados con riesgo eléctrico, uso de herramientas y trabajo en campo. Conocer los mecanismos de reporte de accidentes, incidentes, actos y condiciones inseguras. Identificar las rutas de evacuación, puntos de encuentro y roles en el plan de emergencias. Aplicar prácticas de autocuidado y comportamiento seguro durante la ejecución de sus actividades laborales. Fortalecer la cultura de prevención, participando activamente en las acciones del SG‑SST. | G5: 4 | H5: Magistral interactiva con el trabajador | I5: Evaluacion Oral y Escrita con calificación | J5: Registro de asistencia, evaluacion | K5: Trabajadores nuevos o con inducciòn superior a 1 año | L5: ESSA EPM Servicios de mantenimiento de líneas de transmisión de energía CW261422 | M5: COORDINADOR HSEQ | N5: 1 | Z5: =IF(COUNTA(PlanTrabajo4[[#This Row],[ENE]:[DIC]])=0," ",(COUNTIF(PlanTrabajo4[[#This Row],[ENE]:[DIC]],"=2"))/(COUNTA(PlanTrabajo4[[#This Row],[ENE]:[DIC]]))) -> 0 | AA5: Se realiza cada vez que ingresa personal o se presenta vencimiento de induccion ( 1 año)
A6: INTERVENCION DEL RIESGO | B6: PLAN DE EMERGENCIAS | C6: Plan atención amergencias | D6: PROGRAMA DE GESTION/MATRIZ DE PELIGROS | E6: Capacitar a los trabajadores y contratistas en la identificación de amenazas, procedimientos y acciones a seguir frente a situaciones de emergencia, con el fin de prevenir lesiones, minimizar daños a las personas, instalaciones y al medio ambiente, y asegurar una respuesta eficaz, organizada y oportuna durante la ocurrencia de eventos como incendios, accidentes laborales, emergencias eléctricas, naturales o tecnológicas, de acuerdo con el Plan de Atención de Emergencias del proyecto | F6: Actuar de manera segura y ordenada frente a una emergencia. Conocer su rol dentro del Plan de Atención de Emergencias. Utilizar correctamente rutas de evacuación y equipos básicos. Contribuir a una respuesta efectiva, reduciendo riesgos y consecuencias. | G6: 2 | H6: Teórico- Práctica | I6: Evaluación escrita y/o Taller | J6: Registro de asistencia y evaluación y/o taller y/o certificado | K6: Liniero I, Liniero II, Jefe de trabajos, vigía de prevención ( todos los operativos) | L6: ESSA EPM Servicios de mantenimiento de líneas de transmisión de energía CW261422 | M6: COORDINADOR HSEQ | O6: 1 | Z6: =IF(COUNTA(PlanTrabajo4[[#This Row],[ENE]:[DIC]])=0," ",(COUNTIF(PlanTrabajo4[[#This Row],[ENE]:[DIC]],"=2"))/(COUNTA(PlanTrabajo4[[#This Row],[ENE]:[DIC]]))) -> 0 | AA6: Tema habilitación
A7: INTERVENCION DEL RIESGO | B7: REQUISITOS LEGALES | C7: Tema 1. Fundamentos de la seguridad y salud en el trabajo ( Incluye responsabilidad legal) | D7: HABILITACION | E7: Capacitar y fortalecer los conocimientos del personal en los fundamentos de la Seguridad y Salud en el Trabajo, con el fin de prevenir accidentes laborales y enfermedades de origen laboral, garantizar el cumplimiento del marco legal vigente, promover el respeto por los derechos y responsabilidades de trabajadores y empleador, y resaltar la importancia del correcto diligenciamiento de la documentación del SG‑SST como herramienta preventiva y legal. | F7: Fortalecer conocimientos en los conceptos básicos de Seguridad y Salud en el Trabajo (SST). Reconocer el marco legal aplicable en SST, incluyendo normas nacionales y los principios generales de la Norma ISO 45001. Identificar los derechos y responsabilidades del trabajador y del empleador frente a la seguridad y salud en el trabajo ( incluyendo generalidades de tipo legal). Comprender la importancia del correcto diligenciamiento y gestión de la documentación del SG‑SST. Promover conductas seguras y una cultura de autocuidado y prevención | G7: 2 | H7: Magistral interactiva con el trabajador | I7: Evaluación escrita y/o Taller | J7: Registro de asistencia y evaluación y/o taller y/o certificado | K7: Liniero I, Liniero II, Jefe de trabajos, vigía de prevención ( todos los operativos) | L7: ESSA EPM Servicios de mantenimiento de líneas de transmisión de energía CW261422 | M7: COORDINADOR HSEQ | O7: 1 | Z7: =IF(COUNTA(PlanTrabajo4[[#This Row],[ENE]:[DIC]])=0," ",(COUNTIF(PlanTrabajo4[[#This Row],[ENE]:[DIC]],"=2"))/(COUNTA(PlanTrabajo4[[#This Row],[ENE]:[DIC]]))) -> 0 | AA7: Tema habilitación
A8: INTERVENCION DEL RIESGO | B8: MATRIZ DE PELIGROS | C8: Tema 2: Identificación de Peligros y Evaluación de Riesgos (IPER) | D8: MATRIZ DE PELIGROS | E8: Capacitar y fortalecer los conocimientos del en la Identificación de Peligros y Evaluación de Riesgos (IPER), con el fin de reconocer los peligros presentes en las actividades del proyecto, evaluar los riesgos asociados de acuerdo con la matriz de riesgos, y aplicar medidas de control eficaces que permitan prevenir accidentes de trabajo, enfermedades laborales y eventos graves o fatales. | F8: Identificar los tipos de peligros presentes en el proyecto (físicos, químicos, biológicos, ergonómicos, psicosociales, mecánicos, eléctricos, locativos, públicos y naturales), de acuerdo con la matriz de riesgos del proyecto. Reconocer los peligros críticos y prioritarios en actividades del sector eléctrico y de la construcción. Comprender los métodos para identificar peligros en campo y en planeación de trabajos. Aplicar criterios básicos para evaluar riesgos (probabilidad, consecuencia y nivel de riesgo). identificar y establecer controles adecuados siguiendo la jerarquía de control. | G8: 2 | H8: Teórico- Práctica | I8: Evaluación escrita y/o Taller | J8: Registro de asistencia y evaluación y/o taller y/o certificado | K8: Liniero I, Liniero II, Jefe de trabajos, vigía de prevención ( todos los operativos) | L8: ESSA EPM Servicios de mantenimiento de líneas de transmisión de energía CW261422 | M8: COORDINADOR HSEQ | O8: 1 | Z8: =IF(COUNTA(PlanTrabajo4[[#This Row],[ENE]:[DIC]])=0," ",(COUNTIF(PlanTrabajo4[[#This Row],[ENE]:[DIC]],"=2"))/(COUNTA(PlanTrabajo4[[#This Row],[ENE]:[DIC]]))) -> 0 | AA8: Tema habilitación
A9: INTERVENCION DEL RIESGO | B9: PROMOCION Y PREVENCIÓN | C9: Tema 5. Reporte de accidentes e incidentes de trabajo | D9: REQUISITO LEGAL | E9: Capacitar y fortalecer los conocimientos sobre el reporte oportuno de accidentes e incidentes de trabajo, con el fin de prevenir la repetición de eventos, mejorar las condiciones de seguridad, cumplir con los requisitos legales y promover la participación activa de los trabajadores en la investigación de los eventos. | F9: Comprender qué es un accidente de trabajo y qué es un incidente de trabajo. Reconocer la importancia del reporte inmediato de accidentes e incidentes. Conocer el tiempo de reporte por parte del trabajador (inmediato). Identificar el rol y la participación del trabajador en la investigación de accidentes e incidentes. Fortalecer la cultura de prevención, autocuidado y reporte oportuno. | G9: 2 | H9: Teórica | I9: Evaluación escrita y/o Taller | J9: Registro de asistencia y evaluación y/o taller y/o certificado | K9: Liniero I, Liniero II, Jefe de trabajos, vigía de prevención ( todos los operativos) | L9: ESSA EPM Servicios de mantenimiento de líneas de transmisión de energía CW261422 | M9: COORDINADOR HSEQ | O9: 1 | Z9: =IF(COUNTA(PlanTrabajo4[[#This Row],[ENE]:[DIC]])=0," ",(COUNTIF(PlanTrabajo4[[#This Row],[ENE]:[DIC]],"=2"))/(COUNTA(PlanTrabajo4[[#This Row],[ENE]:[DIC]]))) -> 0 | AA9: Tema habilitación
A10: INTERVENCION DEL RIESGO | B10: PROMOCION Y PREVENCIÓN | C10: Tema 3. Técnicas de Observación y Reporte actos y condiciones inseguras | D10: CONTROL DE ACCIDENTALIDAD / PROGRAMA DE GESTION | E10: Capacitar y fortalecer los conocimientos del personal en las técnicas de observación y reporte de actos y condiciones inseguras, con el fin de identificar oportunamente situaciones de riesgo, comunicarlas de manera efectiva y registrar correctamente la información, contribuyendo así a la prevención de accidentes de trabajo y enfermedades laborales | F10: Capacitar y fortalecer conocimientos en los métodos para observar actos y condiciones inseguras durante la ejecución de labores. Aplicar técnicas de comunicación efectiva para reportar actos y condiciones inseguras de forma clara, oportuna y respetuosa. Utilizar adecuadamente el formato de registro de observación establecido por la empresa. Promover una cultura de prevención, autocuidado y reporte oportuno. | G10: 2 | H10: Teórico- Práctica | I10: Evaluación escrita y/o Taller | J10: Registro de asistencia y evaluación y/o taller y/o certificado | K10: Liniero I, Liniero II, Jefe de trabajos, vigía de prevención ( todos los operativos) | L10: ESSA EPM Servicios de mantenimiento de líneas de transmisión de energía CW261422 | M10: COORDINADOR HSEQ | O10: 1 | Z10: =IF(COUNTA(PlanTrabajo4[[#This Row],[ENE]:[DIC]])=0," ",(COUNTIF(PlanTrabajo4[[#This Row],[ENE]:[DIC]],"=2"))/(COUNTA(PlanTrabajo4[[#This Row],[ENE]:[DIC]]))) -> 0 | AA10: Tema habilitación
A11: PROCESO DE INDUCCION / REINDUCCIÒN | B11: GESTIÓN DEL RIESGOS PRIORITARIOS | C11: Seguridad Eléctrica: Tema 1: Identificación de riesgos, medidas de control, roles y responsabilidades, inspecciones de seguridad. | D11: PROGRAMA DE GESTION/MATRIZ DE PELIGROS | E11: Capacitar y fortalecer los conocimientos proporcionando herramientas para la identificación de riesgos eléctricos, resaltando la importancia del cumplimiento de las Reglas de Oro, el respeto de las distancias mínimas de seguridad, y el uso adecuado de equipos de control como medida preventiva, para garantizar la ejecución segura de actividades en Alta, Media y Baja Tensión, conforme a los procedimientos establecidos y la normativa vigente. | F11: Identificar los riesgos eléctricos asociados a trabajos en AT, MT y BT. Comprender y aplicar las Reglas de Oro de la Seguridad Eléctrica. Reconocer la importancia de mantener distancias de seguridad mínimas. Utilizar adecuadamente los equipos de control del riesgo eléctrico: GPS, distanciómetro, pértigas, guantes dieléctricos, detectores de tensión, entre otros. Aplicar medidas de control generales en áreas de trabajo, según tipo de personal (advertido, calificado). Diferenciar roles y responsabilidades del personal especialista y NO especialista. Realizar inspección de áreas de trabajo e identificación de condiciones eléctricas. Reconocer y respetar las distancias de seguridad para cada tipo de personal. | G11: 2 | H11: Teórico- Práctica | I11: Evaluación escrita y/o Taller | J11: Registro de asistencia y evaluación y/o taller y/o certificado | K11: Liniero I, Liniero II, Jefe de trabajos, vigía de prevención ( todos los operativos) | L11: ESSA EPM Servicios de mantenimiento de líneas de transmisión de energía CW261422 | M11: COORDINADOR HSEQ | P11: 1 | Z11: =IF(COUNTA(PlanTrabajo4[[#This Row],[ENE]:[DIC]])=0," ",(COUNTIF(PlanTrabajo4[[#This Row],[ENE]:[DIC]],"=2"))/(COUNTA(PlanTrabajo4[[#This Row],[ENE]:[DIC]]))) -> 0 | AA11: Tema habilitación
A12: INTERVENCION DEL RIESGO | B12: PROGRAMA DE GESTIÓN PARA EL RIESGO ELÉCTRICO / PROGRAMA PARA LA GESTIÓN DEL RIESGO MECÁNICO | C12: Intervención vegetación ( obras): Tema 1. Identificación de peligros, controles planeación segura | D12: PROGRAMA DE GESTION/MATRIZ DE PELIGROS | E12: Capacitar y fortalecer los conocimientos para la identificación de peligros, aplicación de controles y planeación segura en actividades de intervención y mantenimiento de vegetación, garantizando la ejecución segura de los trabajos asociados a obras que incluyan o no actividades a proximidad a redes eléctricas energizadas o sin tensión, de acuerdo con los procedimientos establecidos y el control del riesgo eléctrico. | F12: Reconocer los peligros asociados a la intervención y mantenimiento de vegetación en diferentes entornos. Aplicar medidas de control adecuadas para minimizar riesgos durante la ejecución de las actividades. Planear de manera segura las tareas de mantenimiento, considerando condiciones del entorno y cercanía a redes eléctricas. Fortalecer la cultura de seguridad en el equipo de trabajo, promoviendo la prevención y el autocuidado. Garantizar el cumplimiento de los procedimientos establecidos y normativas vigentes en materia de seguridad eléctrica. Desarrollar habilidades prácticas para la toma de decisiones seguras en situaciones de riesgo eléctrico. | G12: 2 | H12: Teórico- Práctica | I12: Evaluación escrita y/o Taller | J12: Registro de asistencia y evaluación y/o taller y/o certificado | K12: Liniero I, Liniero II, Jefe de trabajos, vigía de prevención ( todos los operativos) | L12: ESSA EPM Servicios de mantenimiento de líneas de transmisión de energía CW261422 | M12: COORDINADOR HSEQ | P12: 1 | Z12: =IF(COUNTA(PlanTrabajo4[[#This Row],[ENE]:[DIC]])=0," ",(COUNTIF(PlanTrabajo4[[#This Row],[ENE]:[DIC]],"=2"))/(COUNTA(PlanTrabajo4[[#This Row],[ENE]:[DIC]]))) -> 0 | AA12: Tema habilitación
A13: INTERVENCION DEL RIESGO | B13: PROGRAMA DE SVE OSTEOMUSCULAR | C13: Tema: Manipulación y transporte de cargas, posturas y trabajo repetitivo. | D13: PROGRAMA DE GESTION/MATRIZ DE PELIGROS | E13: Capacitar y fortalecer los conocimientos , brindando herramientas prácticas para conocer y aplicar técnicas seguras en la manipulación y transporte de cargas, así como medidas preventivas frente a posturas forzadas, estáticas, prolongadas y trabajos repetitivos, con el fin de prevenir y controlar los trastornos osteomusculares y proteger la salud de los trabajadores. | F13: Reconocer los riesgos ergonómicos presentes en las actividades del sector eléctrico y construcción. Aplicar técnicas seguras de manipulación y transporte de cargas. Implementar medidas preventivas frente a posturas forzadas, estáticas y prolongadas. Identificar los riesgos asociados al trabajo repetitivo y aplicar prácticas de control. Prevenir la aparición de trastornos osteomusculares mediante buenas prácticas ergonómicas. | G13: 2 | H13: Teórico- Práctica | I13: Evaluación escrita y/o Taller | J13: Registro de asistencia y evaluación y/o taller y/o certificado | K13: Liniero I, Liniero II, Jefe de trabajos, vigía de prevención ( todos los operativos) | L13: ESSA EPM Servicios de mantenimiento de líneas de transmisión de energía CW261422 | M13: COORDINADOR HSEQ | P13: 1 | Z13: =IF(COUNTA(PlanTrabajo4[[#This Row],[ENE]:[DIC]])=0," ",(COUNTIF(PlanTrabajo4[[#This Row],[ENE]:[DIC]],"=2"))/(COUNTA(PlanTrabajo4[[#This Row],[ENE]:[DIC]]))) -> 0 | AA13: Tema habilitación
A14: PARTICIPACION Y CONSULTA | B14: INVESTIGACION DE ACCIDENTES Y INCIDENTES/REPORTE DE ACTOS Y CONDICIONES | C14: Reporte de accidentes, incidentes, actos inseguros y lineamientos para su investigaciòn | D14: REQUISITO LEGAL | E14: Capacitar y fortalecer los conocimientos sobre los lineamientos para el reporte e investigación de accidentes, incidentes y actos inseguros, asegurando el cumplimiento de la Resolución 1401 de 2007 y del procedimiento interno PR‑HSEQ‑05, con el fin de identificar causas, prevenir la repetición de eventos y mejorar las condiciones de seguridad y salud en el trabajo. | F14: Capacitar y fortalecer conocimientos en los lineamientos para el reporte de accidentes, incidentes y actos inseguros. Conocer y aplicar los requisitos de la Resolución 1401 de 2007 para la investigación de accidentes e incidentes de trabajo. Aplicar correctamente el procedimiento PR‑HSEQ‑05 – Reporte e Investigación de Incidentes y Accidentes de Trabajo. Reconocer la importancia del reporte oportuno e inmediato. Participar activamente en el proceso de investigación como herramienta de prevención. | G14: 2 | H14: Magistral interactiva con el trabajador | I14: Evaluación escrita con calificación | J14: Registro de asistencia, evaluacion y/o certificado | K14: Todos los trabajadores asociado al contrato | L14: ESSA EPM Servicios de mantenimiento de líneas de transmisión de energía CW261422 | M14: ARL SURA/COORDINADOR HSEQ | P14: 1 | Z14: =IF(COUNTA(PlanTrabajo4[[#This Row],[ENE]:[DIC]])=0," ",(COUNTIF(PlanTrabajo4[[#This Row],[ENE]:[DIC]],"=2"))/(COUNTA(PlanTrabajo4[[#This Row],[ENE]:[DIC]]))) -> 0
A15: INTERVENCION DEL RIESGO | B15: PROGRAMA DE GESTIÓN PARA EL RIESGO ELÉCTRICO | C15: Seguridad Eléctrica: Tema 2: Distancias de seguridad, técnica de trabajo, trabajo en proximidad | D15: PROGRAMA DE GESTION/MATRIZ DE PELIGROS | E15: Capacitar y fortalecer los conocimientos en seguridad eléctrica, mediante la planeación y aplicación de distancias de seguridad, el uso de técnicas de trabajo seguro y la identificación, evaluación y valoración de riesgos en actividades realizadas en proximidad a redes eléctricas, con el fin de prevenir accidentes graves o fatales y garantizar el cumplimiento de los procedimientos establecidos. | F15: Capacitar y fortalecer conocimientos en la planeación y aplicación de distancias de seguridad para personal especialista. Aplicar técnicas de trabajo seguro en actividades eléctricas. Identificar los peligros eléctricos presentes en trabajos en proximidad a redes. Evaluar y valorar los riesgos asociados al trabajo en proximidad, de acuerdo con la matriz de riesgos y el método IPER. Aplicar controles efectivos que reduzcan la probabilidad de contacto eléctrico o arco eléctrico. | G15: 2 | H15: Teórico- Práctica | I15: Evaluación escrita y/o Taller | J15: Registro de asistencia y evaluación y/o taller y/o certificado | K15: Liniero I, Liniero II, Jefe de trabajos, vigía de prevención ( todos los operativos) | L15: ESSA EPM Servicios de mantenimiento de líneas de transmisión de energía CW261422 | M15: COORDINADOR HSEQ | P15: 1 | Z15: =IF(COUNTA(PlanTrabajo4[[#This Row],[ENE]:[DIC]])=0," ",(COUNTIF(PlanTrabajo4[[#This Row],[ENE]:[DIC]],"=2"))/(COUNTA(PlanTrabajo4[[#This Row],[ENE]:[DIC]]))) -> 0 | AA15: Tema habilitación
A16: INTERVENCION DEL RIESGO | B16: CONDICIONES DE SEGURIDAD/INSPECCIONES | C16: Señalizacion y tipos de señalizacion: Inspecciones ( formatos y correcto diligenciamiento) | D16: MATRIZ DE PELIGROS | E16: Proporcionar a los trabajadores los conocimientos básicos y prácticos sobre señalización de seguridad y la realización de inspecciones de seguridad, que les permitan identificar los riesgos presentes en las diferentes áreas de la empresa, utilizar correctamente los formatos de inspección, y apoyar la implementación efectiva de las medidas de control. | F16: Reconocer la importancia de la señalización como medida preventiva. Identificar los tipos de señalización de seguridad y su correcta aplicación en el lugar de trabajo. Comprender qué es una inspección de seguridad y por qué es fundamental para la prevención de accidentes. Aplicar correctamente los formatos de inspección, diligenciándolos de forma clara y objetiva. Identificar actos y condiciones inseguras durante las inspecciones. Contribuir activamente en la propuesta y seguimiento de medidas de control. | G16: 2 | H16: Magistral interactiva con el trabajador | I16: Evaluación escrita con calificación | J16: Registro de asistencia, evaluacion y/o certificado | K16: Todos los trabajadores asociado al contrato | L16: ESSA EPM Servicios de mantenimiento de líneas de transmisión de energía CW261422 | M16: ARL SURA/COORDINADOR HSEQ | Q16: 1 | Z16: =IF(COUNTA(PlanTrabajo4[[#This Row],[ENE]:[DIC]])=0," ",(COUNTIF(PlanTrabajo4[[#This Row],[ENE]:[DIC]],"=2"))/(COUNTA(PlanTrabajo4[[#This Row],[ENE]:[DIC]]))) -> 0
A17: INTERVENCION DEL RIESGO | B17: PROGRAMA DE RIESGO PSICOSOCIAL | C17: Habilidades blandas: Tema 1. '¿Lideres o Jefes?: Conceptos Liderazgo – Tipos de Liderazgo – Proceso de Liderazgo – Anti líder – Recomendaciones | D17: PROGRAMA DE GESTION/REQUISITO LEGAL/HABILITACION | E17: Capacitar y fortalecer los conocimientos del personal en habilidades blandas asociadas al liderazgo, sensibilizando sobre la importancia de los estilos de mando y los tipos de liderazgo, con el fin de fortalecer las habilidades del equipo de trabajo que influyen en las actuaciones técnicas, ambientales y de seguridad y salud en el trabajo | F17: Sensibilizar al personal acerca de la diferencia entre jefe y líder. Reconocer los conceptos básicos de liderazgo y su aplicación en campo. Identificar los diferentes tipos de liderazgo y su impacto en los equipos de trabajo. Comprender el proceso de liderazgo y su relación con la cultura de seguridad. Identificar conductas del anti‑líder y sus consecuencias en el desempeño del equipo. Brindar recomendaciones prácticas para fortalecer un liderazgo positivo en el sector eléctrico y construcción. | G17: 2 | H17: Magistral interactiva con el trabajador | I17: Evaluación escrita y/o Taller | J17: Registro de asistencia y evaluación y/o taller y/o certificado | K17: Liniero I, Liniero II, Jefe de trabajos, vigía de prevención ( todos los operativos) | L17: ESSA EPM Servicios de mantenimiento de líneas de transmisión de energía CW261422 | M17: COORDINADOR HSEQ | Q17: 1 | Z17: =IF(COUNTA(PlanTrabajo4[[#This Row],[ENE]:[DIC]])=0," ",(COUNTIF(PlanTrabajo4[[#This Row],[ENE]:[DIC]],"=2"))/(COUNTA(PlanTrabajo4[[#This Row],[ENE]:[DIC]]))) -> 0 | AA17: Tema habilitación
A18: INTERVENCION DEL RIESGO | B18: PROGRAMA DE RIESGO PSICOSOCIAL | C18: Tema 2. 'Liderazgo Inspirador: Empoderamiento liderazgo en comportamientos seguros – Liderazgo Transformacional | D18: PROGRAMA DE GESTION/REQUISITO LEGAL/HABILITACION | E18: Capacitar y fortalecer los conocimientos del personal enl liderazgo inspirador o transformacional, brindando herramientas que permitan incentivar cambios de comportamiento orientados a la ejecución de actividades seguras y a la generación de ambientes de trabajo saludables. | F18: Dar a conocer el concepto de liderazgo inspirador y transformacional aplicado al sector eléctrico y de la construcción. Fortalecer las capacidades de liderazgo para influir en comportamientos seguros. Promover el empoderamiento del personal como estrategia para la prevención de accidentes. Reconocer la relación entre liderazgo, cultura de seguridad y ambientes laborales saludables. Brindar herramientas prácticas para generar cambios positivos de comportamiento en los equipos de trabajo | G18: 2 | H18: Magistral interactiva con el trabajador | I18: Evaluación escrita y/o Taller | J18: Registro de asistencia y evaluación y/o taller y/o certificado | K18: Liniero I, Liniero II, Jefe de trabajos, vigía de prevención ( todos los operativos) | L18: ESSA EPM Servicios de mantenimiento de líneas de transmisión de energía CW261422 | M18: COORDINADOR HSEQ | Q18: 1 | Z18: =IF(COUNTA(PlanTrabajo4[[#This Row],[ENE]:[DIC]])=0," ",(COUNTIF(PlanTrabajo4[[#This Row],[ENE]:[DIC]],"=2"))/(COUNTA(PlanTrabajo4[[#This Row],[ENE]:[DIC]]))) -> 0 | AA18: Tema habilitación
A19: INTERVENCION DEL RIESGO | B19: RIESGO SOCIOPOLITICO | C19: Riesgo Sociopolítico | D19: MATRIZ DE PELIGROS | E19: Capacitar y fortalecer los conocimientos del personal sobre los riesgos sociopolíticos presentes en el entorno laboral, dando a conocer las principales amenazas y las medidas de seguridad a aplicar ante situaciones de riesgo como presencia de artefactos explosivos, conflicto armado o social, secuestro, extorsión, hurto calificado u otros eventos asociados. | F19: Dar a conocer el concepto de riesgo sociopolítico y su impacto en las actividades operativas. Identificar los principales riesgos sociopolíticos que pueden afectar al sector eléctrico y construcción. Sensibilizar al personal sobre las medidas preventivas y de autoprotección. Brindar lineamientos generales de actuación ante la identificación de artefactos explosivos. Fortalecer la capacidad de reacción ante situaciones de conflicto social o armado, secuestro y extorsión. | G19: 2 | H19: Magistral interactiva con el trabajador | I19: Evaluacion Escrita con calificación | J19: Registro de asistencia, evaluacion y/o certificado | K19: Todos los trabajadores asociado al contrato | L19: ESSA EPM Servicios de mantenimiento de líneas de transmisión de energía CW261422 | M19: ARL SURA/COORDINADOR HSEQ | Q19: 1 | Z19: =IF(COUNTA(PlanTrabajo4[[#This Row],[ENE]:[DIC]])=0," ",(COUNTIF(PlanTrabajo4[[#This Row],[ENE]:[DIC]],"=2"))/(COUNTA(PlanTrabajo4[[#This Row],[ENE]:[DIC]]))) -> 0
A20: INTERVENCION DEL RIESGO | B20: GESTIÓN DEL RIESGOS PRIORITARIOS | C20: Trabajo seguro en obras civiles ( incluye excavación) | D20: CONTROL DE ACCIDENTALIDAD / PROGRAMA DE GESTION/MATRIZ DE PELIGROS | E20: Fortalecer en los trabajadores practicas seguras en la ejecución actividades de obra civil con el fin pueda identificar riesgos,peligros y controles establecidos, uso correcto de epp, uso seguro de herramientas y equipos asignados para la operación | F20: Reconocer los peligros y riesgos críticos asociados a excavaciones y obras civiles en torres de transmisión. Aplicar medidas de control para prevenir derrumbes, atrapamientos, caídas, atropellos y otros incidentes graves. Interpretar y cumplir los procedimientos de trabajo seguro, permisos de excavación y análisis de riesgos . Utilizar correctamente los equipos de protección personal (EPP) requeridos para cada actividad. Identificar condiciones inseguras del terreno, clima y entorno que puedan afectar la estabilidad de excavaciones. Garantizar el uso seguro de maquinaria y herramientas en actividades de obra civil. Actuar adecuadamente frente a situaciones de emergencia, como derrumbes, inundaciones o rescates en excavaciones. Promover una cultura preventiva, responsabilidad individual y trabajo seguro en campo. | G20: 2 | H20: Magistral interactiva con el trabajador | I20: Evaluacion Escrita con calificación | J20: Registro de asistencia, evaluacion y/o certificado | K20: Todos los trabajadores asociado al contrato | L20: ESSA EPM Servicios de mantenimiento de líneas de transmisión de energía CW261422 | M20: ARL SURA/COORDINADOR HSEQ | Q20: 1 | Z20: =IF(COUNTA(PlanTrabajo4[[#This Row],[ENE]:[DIC]])=0," ",(COUNTIF(PlanTrabajo4[[#This Row],[ENE]:[DIC]],"=2"))/(COUNTA(PlanTrabajo4[[#This Row],[ENE]:[DIC]]))) -> 0
A21: INTERVENCION DEL RIESGO | B21: PROMOCION Y PREVENCIÓN | C21: Tema 4. Promoción de la Cultura de Seguridad | D21: PROGRAMA DE GESTION/REQUISITO LEGAL/HABILITACION | E21: Capacitar y fortalecer los conocimientos del personal, promoviendo una cultura de seguridad basada en la prevención de riesgos, el autocuidado y el cumplimiento de las normas de seguridad, con el fin de reducir accidentes e incidentes de trabaj | F21: Importancia del uso adecuado de los Equipos de Protección Personal (EPP). Importancia del cumplimiento de normas y procedimientos de seguridad. Comprensión de accidentes e incidentes de trabajo y la importancia del reporte oportuno. | G21: 2 | H21: Magistral interactiva con el trabajador | I21: Evaluación escrita y/o Taller | J21: Registro de asistencia y evaluación y/o taller y/o certificado | K21: Liniero I, Liniero II, Jefe de trabajos, vigía de prevención ( todos los operativos) | L21: ESSA EPM Servicios de mantenimiento de líneas de transmisión de energía CW261422 | M21: COORDINADOR HSEQ | R21: 1 | Z21: =IF(COUNTA(PlanTrabajo4[[#This Row],[ENE]:[DIC]])=0," ",(COUNTIF(PlanTrabajo4[[#This Row],[ENE]:[DIC]],"=2"))/(COUNTA(PlanTrabajo4[[#This Row],[ENE]:[DIC]]))) -> 0 | AA21: Tema habilitación
A22: INTERVENCION DEL RIESGO | B22: PROGRAMA ESTILOS DE VIDA SALUDABLE | C22: Prevenciòn al consumo de drogas y alcohol | D22: PROGRAMA DE GESTION/MATRIZ DE PELIGROS | E22: Capacitar y fortalecer los conocimientos del personal sobre la prevención del consumo de drogas y alcohol, promoviendo estilos de vida saludables y seguros, que contribuyan a la prevención de accidentes, enfermedades y riesgos laborales. | F22: Generar conciencia sobre los daños físicos y de salud que produce el consumo de sustancias psicoactivas y alcohol. Reconocer las consecuencias laborales del consumo de alcohol y drogas, especialmente en actividades de alto riesgo del sector eléctrico y de la construcción. Identificar los impactos sociales y familiares asociados al consumo de sustancias psicoactivas y alcohol. Promover el autocuidado y la toma de decisiones responsables, fomentando una vida sana, segura y libre de adicciones. Prevenir enfermedades, accidentes e incidentes de trabajo derivados del consumo de alcohol y drogas. | G22: 2 | H22: Magistral interactiva con el trabajador | I22: Evaluacion Escrita con calificación | J22: Registro de asistencia, evaluacion y/o certificado | K22: Todos los trabajadores asociado al contrato | L22: ESSA EPM Servicios de mantenimiento de líneas de transmisión de energía CW261422 | M22: ARL SURA/COORDINADOR HSEQ | R22: 1 | Z22: =IF(COUNTA(PlanTrabajo4[[#This Row],[ENE]:[DIC]])=0," ",(COUNTIF(PlanTrabajo4[[#This Row],[ENE]:[DIC]],"=2"))/(COUNTA(PlanTrabajo4[[#This Row],[ENE]:[DIC]]))) -> 0
A23: INTERVENCION DEL RIESGO | B23: PROGRAMA DE SVE OSTEOMUSCULAR | C23: Riesgo Biomecanico en actividades operativas | D23: PROGRAMA DE GESTION/MATRIZ DE PELIGROS | E23: Capacitar y fortalecer los conocimientos del personal sobre el riesgo biomecánico presente en las actividades operativas, brindando herramientas para la prevención de lesiones musculoesqueléticas y la ejecución segura de las labores. | F23: Identificar el riesgo biomecánico asociado a las actividades operativas propias del sector eléctrico y de la construcción. Prevenir lesiones musculoesqueléticas, mediante la adopción de posturas correctas y prácticas de trabajo seguro. Aplicar técnicas adecuadas de manipulación manual de materiales, reduciendo la sobrecarga física y el esfuerzo innecesario. Utilizar correctamente herramientas y equipos, minimizando movimientos repetitivos, posturas forzadas y esfuerzos prolongados. Promover el autocuidado y la conciencia preventiva como parte de la cultura de seguridad y salud en el trabajo. | G23: 2 | H23: Magistral interactiva con el trabajador | I23: Evaluación escrita con calificación | J23: Registro de asistencia, evaluacion y/o certificado | K23: Todos los trabajadores asociado al contrato | L23: ESSA EPM Servicios de mantenimiento de líneas de transmisión de energía CW261422 | M23: ARL SURA/COORDINADOR HSEQ | R23: 1 | Z23: =IF(COUNTA(PlanTrabajo4[[#This Row],[ENE]:[DIC]])=0," ",(COUNTIF(PlanTrabajo4[[#This Row],[ENE]:[DIC]],"=2"))/(COUNTA(PlanTrabajo4[[#This Row],[ENE]:[DIC]]))) -> 0 | AA23: Tema habilitación
A24: PLAN DE EMERGENCIAS | B24: PLAN DE EMERGENCIAS | C24: Control del fuego y procedimiento seguro de evacuación | D24: PROGRAMA DE GESTION/REQUISITO LEGAL/HABILITACION/MATRIZ DE PELIGROS | E24: Capacitar a los trabajadores para prevenir y controlar con seguridad conatos de incendio, mediante el uso adecuado de extintores, la identificación de rutas de evacuación seguras y la correcta aplicación de los procedimientos de evacuación, con el fin de proteger la vida y minimizar daños durante una emergencia. | F24: Identificar los riesgos de incendio presentes en su área de trabajo. Reconocer los tipos de fuego y el extintor adecuado para cada caso. Aplicar correctamente la técnica de uso del extintor de forma segura. Actuar de manera rápida y ordenada ante un conato de incendio. Identificar y utilizar las rutas de evacuación seguras establecidas. Ejecutar el procedimiento de evacuación sin generar pánico. Reconocer cuándo intentar controlar el fuego y cuándo evacuar de inmediato. Seguir las instrucciones de las brigadas y líderes de evacuación. Contribuir a la protección de la vida y reducción de daños durante una emergencia. | G24: 2 | H24: Teórico - Práctica | I24: Evaluación escrita con calificación | J24: Registro de asistencia, evaluacion y/o certificado | K24: Todos los trabajadores asociado al contrato | L24: ESSA EPM Servicios de mantenimiento de líneas de transmisión de energía CW261422 | M24: ARL SURA/COORDINADOR HSEQ | R24: 1 | Z24: =IF(COUNTA(PlanTrabajo4[[#This Row],[ENE]:[DIC]])=0," ",(COUNTIF(PlanTrabajo4[[#This Row],[ENE]:[DIC]],"=2"))/(COUNTA(PlanTrabajo4[[#This Row],[ENE]:[DIC]]))) -> 0
A25: INTERVENCION DEL RIESGO | B25: PROGRAMA DE RIESGO PSICOSOCIAL | C25: Tema 3. Formación en lideres en seguridad y salud en el trabajo bajo el Fortalecimiento en Habilidades blandas | D25: PROGRAMA DE GESTION/REQUISITO LEGAL/HABILITACION/MATRIZ DE PELIGROS | E25: Fortalecer y motivar en los trabajadores el desarrollo de una conciencia activa en seguridad y salud en el trabajo, fortaleciendo sus habilidades blandas y su rol como líderes en seguridad, integrando comportamientos seguros en el desarrollo de sus actividades cotidianas. | F25: Reconocer la importancia de la Seguridad y Salud en el Trabajo como parte de su responsabilidad individual y colectiva. Desarrollar una conciencia activa en seguridad, aplicando el autocuidado en sus actividades diarias. Identificar su rol como líder en seguridad, independientemente de su cargo o función. Fortalecer habilidades blandas clave como la comunicación efectiva, el trabajo en equipo y la empatía. Promover y reforzar comportamientos seguros en sí mismos y en sus compañeros de trabajo. Comunicar de manera asertiva actos y condiciones inseguras. Participar activamente en la prevención de accidentes e incidentes. Integrar la seguridad como un valor permanente en el desarrollo de sus labores cotidiana | G25: 2 | H25: Magistral interactiva con el trabajador | I25: Evaluación escrita y/o Taller | J25: Registro de asistencia y evaluación y/o taller y/o certificado | K25: Liniero I, Liniero II, Jefe de trabajos, vigía de prevención ( todos los operativos) | L25: ESSA EPM Servicios de mantenimiento de líneas de transmisión de energía CW261422 | M25: COORDINADOR HSEQ | R25: 1 | Z25: =IF(COUNTA(PlanTrabajo4[[#This Row],[ENE]:[DIC]])=0," ",(COUNTIF(PlanTrabajo4[[#This Row],[ENE]:[DIC]],"=2"))/(COUNTA(PlanTrabajo4[[#This Row],[ENE]:[DIC]]))) -> 0 | AA25: Tema habilitación
A26: INTERVENCION DEL RIESGO | B26: PROGRAMA DE GESTIÓN DE RIESGO QUIMICO | C26: Riesgo quimico: Manipulaciòn segura de sustancias quimicas,almacenamiento, hojas de seguridad, matriz de compatibilidad | D26: PROGRAMA DE GESTION/REQUISITO LEGAL/HABILITACION/MATRIZ DE PELIGROS | E26: Dar a conocer al personal los lineamientos para la rotulación, almacenamiento y manipulación segura de sustancias químicas, fortaleciendo la prevención de accidentes, enfermedades laborales y daños al ambiente, conforme a los criterios del Sistema Globalmente Armonizado (SGA). | F26: Identificar el riesgo químico presente en las sustancias utilizadas durante el desarrollo de sus actividades laborales. Reconocer la importancia de la rotulación adecuada de productos químicos, de acuerdo con el Sistema Globalmente Armonizado (SGA). Aplicar prácticas seguras para la manipulación de sustancias químicas, reduciendo la exposición y el riesgo de accidentes. Adoptar lineamientos correctos para el almacenamiento de productos químicos, teniendo en cuenta la compatibilidad química. Interpretar y utilizar adecuadamente las Hojas de Datos de Seguridad (HDS/MSDS) como herramienta fundamental para la prevención de emergencias químicas. Comprender y aplicar la matriz de compatibilidad, evitando reacciones peligrosas entre sustancias químicas. | G26: 2 | H26: Magistral interactiva con el trabajador | I26: Evaluacion Escrita con calificación | J26: Registro de asistencia, evaluacion y/o certificado | K26: Todos los trabajadores asociado al contrato | L26: ESSA EPM Servicios de mantenimiento de líneas de transmisión de energía CW261422 | M26: ARL SURA/COORDINADOR HSEQ | S26: 1 | Z26: =IF(COUNTA(PlanTrabajo4[[#This Row],[ENE]:[DIC]])=0," ",(COUNTIF(PlanTrabajo4[[#This Row],[ENE]:[DIC]],"=2"))/(COUNTA(PlanTrabajo4[[#This Row],[ENE]:[DIC]]))) -> 0
A27: INTERVENCION DEL RIESGO | B27: PROGRAMA DE RIESGO PSICOSOCIAL | C27: Tècnicas de observaciòn: Tipos de Observación – Técnicas de Observación – Tipos de Feedback | D27: PROGRAMA DE GESTION/REQUISITO LEGAL/HABILITACION | E27: Fortalecer las técnicas de observación de conductas seguras e inseguras, aplicando la metodología de Seguridad Basada en el Comportamiento (SBC), con el fin de promover el reporte oportuno de actos y condiciones de seguridad y prevenir la materialización de accidentes de trabajo. | F27: Comprender los principios de la Seguridad Basada en el Comportamiento (SBC) como herramienta preventiva en Seguridad y Salud en el Trabajo. Reconocer los diferentes tipos de observación, aplicables a las actividades operativas y cotidianas. Aplicar técnicas efectivas de observación de conductas, enfocadas en identificar actos y condiciones subestándar. Valorar la importancia del reporte oportuno de actos y condiciones inseguras, como medio para prevenir accidentes de trabajo. Brindar feedback efectivo, respetuoso y constructivo que promueva cambios positivos en el comportamiento seguro. | G27: 2 | H27: Magistral interactiva con el trabajador | I27: Evaluación escrita con calificación | J27: Registro de asistencia, evaluacion y/o certificado | K27: Todos los trabajadores asociado al contrato | L27: ESSA EPM Servicios de mantenimiento de líneas de transmisión de energía CW261422 | M27: ARL SURA/COORDINADOR HSEQ | S27: 1 | Z27: =IF(COUNTA(PlanTrabajo4[[#This Row],[ENE]:[DIC]])=0," ",(COUNTIF(PlanTrabajo4[[#This Row],[ENE]:[DIC]],"=2"))/(COUNTA(PlanTrabajo4[[#This Row],[ENE]:[DIC]]))) -> 0 | AA27: Tema habilitación
A28: INTERVENCION DEL RIESGO | B28: GESTIÓN DEL RIESGOS PRIORITARIOS | C28: Uso y Cuidado Correcto del Equipos y elementos de de Protección Personal (EPP) | D28: PROGRAMA DE GESTION/REQUISITO LEGAL/HABILITACION/MATRIZ DE PELIGROS | E28: Capacitar a los trabajadores en la correcta selección, uso, mantenimiento y almacenamiento del Equipo de Protección Personal (EPP), garantizando su eficacia como medida de control y contribuyendo a la minimización de los riesgos laborales. | F28: Reconocer la importancia del EPP como última barrera de protección frente a los riesgos laborales. Identificar y seleccionar correctamente los elementos de protección personal entregados, de acuerdo con el tipo de riesgo y la actividad a realizar. Utilizar adecuadamente el EPP, garantizando su correcto ajuste y funcionamiento durante la ejecución de las tareas. Aplicar prácticas adecuadas de mantenimiento y limpieza del EPP, prolongando su vida útil y asegurando su efectividad. Almacenar correctamente los elementos de protección personal, evitando su deterioro o contaminación. Promover el autocuidado y la responsabilidad individual, reforzando una cultura de seguridad y prevención en el trabajo | G28: 2 | H28: Magistral interactiva con el trabajador | I28: Taller practico | J28: Registro de asistencia, evaluacion y/o certificado | K28: Todos los trabajadores asociado al contrato | L28: ESSA EPM Servicios de mantenimiento de líneas de transmisión de energía CW261422 | M28: ARL SURA/COORDINADOR HSEQ | S28: 1 | Z28: =IF(COUNTA(PlanTrabajo4[[#This Row],[ENE]:[DIC]])=0," ",(COUNTIF(PlanTrabajo4[[#This Row],[ENE]:[DIC]],"=2"))/(COUNTA(PlanTrabajo4[[#This Row],[ENE]:[DIC]]))) -> 0 | AA28: Tema habilitación
A29: INTERVENCION DEL RIESGO | B29: RIESGO MECANICO | C29: Manipulación segura de herramientas y equipos | D29: PROGRAMA DE GESTION/MATRIZ DE PELIGROS | E29: Capacitar al personal en acciones seguras para la manipulación, cargue, traslado y uso adecuado de herramientas y equipos, con enfoque en la prevención del riesgo mecánico, con el fin de evitar golpes, atrapamientos, choques, cortes y otros accidentes de trabajo. | F29: Identificar el riesgo mecánico asociado a la manipulación de herramientas y equipos durante la ejecución de sus actividades. Reconocer las acciones inseguras que pueden generar golpes, atrapamientos, choques, cortes o aplastamientos. Aplicar técnicas seguras de cargue y traslado de herramientas y equipos, reduciendo el riesgo de accidentes y lesiones. Utilizar correctamente las herramientas y equipos, respetando su diseño, función y procedimientos de seguridad. Inspeccionar previamente las herramientas y equipos, detectando condiciones inseguras antes de su uso. Promover el autocuidado y la responsabilidad individual, fortaleciendo una cultura de prevención frente al riesgo mecánico. | G29: 2 | H29: Magistral interactiva con el trabajador | I29: Evaluación escrita con calificación | J29: Registro de asistencia, evaluacion y/o certificado | K29: Todos los trabajadores asociado al contrato | L29: ESSA EPM Servicios de mantenimiento de líneas de transmisión de energía CW261422 | M29: ARL SURA/COORDINADOR HSEQ | S29: 1 | Z29: =IF(COUNTA(PlanTrabajo4[[#This Row],[ENE]:[DIC]])=0," ",(COUNTIF(PlanTrabajo4[[#This Row],[ENE]:[DIC]],"=2"))/(COUNTA(PlanTrabajo4[[#This Row],[ENE]:[DIC]]))) -> 0 | AA29: Tema habilitación(AD)
A30: INTERVENCION DEL RIESGO | B30: PROGRAMA ESTILOS DE VIDA SALUDABLE | C30: Gestión del estrés y salud Mental | D30: PROGRAMA DE GESTION/REQUISITO LEGAL/HABILITACION/MATRIZ DE PELIGROS | E30: Fortalecer las competencias de los trabajadores en gestión del estrés y cuidado de la salud mental, mediante la adopción de técnicas y estrategias prácticas que favorezcan el equilibrio entre la vida personal y laboral, promoviendo el bienestar integral y el desempeño seguro en el trabajo. | F30: Reconocer el estrés laboral y sus principales causas, identificando signos y síntomas físicos, emocionales y conductuales. Aplicar técnicas básicas de manejo del estrés, que contribuyan al autocontrol emocional y al bienestar mental. Desarrollar estrategias para equilibrar la vida personal y laboral, reduciendo el impacto del estrés en la salud y el desempeño. Fomentar el autocuidado y la conciencia emocional, como factores clave para la prevención de afectaciones a la salud mental. Promover ambientes laborales saludables, basados en el respeto, la comunicación y el apoyo mutuo. | G30: 2 | H30: Magistral interactiva con el trabajador | I30: Evaluación escrita con calificación | J30: Registro de asistencia, evaluacion y/o certificado | K30: Todos los trabajadores asociado al contrato | L30: ESSA EPM Servicios de mantenimiento de líneas de transmisión de energía CW261422 | M30: ARL SURA/COORDINADOR HSEQ | S30: 1 | Z30: =IF(COUNTA(PlanTrabajo4[[#This Row],[ENE]:[DIC]])=0," ",(COUNTIF(PlanTrabajo4[[#This Row],[ENE]:[DIC]],"=2"))/(COUNTA(PlanTrabajo4[[#This Row],[ENE]:[DIC]]))) -> 0 | AA30: Tema habilitación
A31: INTERVENCION DEL RIESGO | B31: GESTIÓN DEL RIESGOS PRIORITARIOS | C31: Cultura de Seguridad ( psicosocial) | D31: PROGRAMA DE GESTION/REQUISITO LEGAL/HABILITACION | E31: Dar a conocer al personal la importancia del reporte de incidentes y condiciones inseguras, fortaleciendo la construcción de una mentalidad proactiva de seguridad, basada en la participación, la prevención y el autocuidado, como parte de una cultura organizacional segura y saludable. | F31: Reconocer la importancia del reporte oportuno de incidentes y condiciones inseguras, como herramienta fundamental para la prevención de accidentes y enfermedades laborales. Identificar barreras psicosociales que limitan el reporte (miedo, indiferencia, normalización del riesgo) y superarlas mediante una comunicación abierta y responsable. Desarrollar una mentalidad proactiva de seguridad, anticipándose a los riesgos antes de que se materialicen en accidentes. Fomentar la participación activa de los trabajadores, promoviendo la corresponsabilidad en la gestión de la seguridad y salud en el trabajo. Fortalecer la conciencia individual y colectiva, integrando el comportamiento seguro en las actividades cotidianas. | G31: 2 | H31: Magistral interactiva con el trabajador | I31: Evaluación escrita con calificación | J31: Registro de asistencia, evaluacion y/o certificado | K31: Todos los trabajadores asociado al contrato | L31: ESSA EPM Servicios de mantenimiento de líneas de transmisión de energía CW261422 | M31: ARL SURA/COORDINADOR HSEQ | T31: 1 | Z31: =IF(COUNTA(PlanTrabajo4[[#This Row],[ENE]:[DIC]])=0," ",(COUNTIF(PlanTrabajo4[[#This Row],[ENE]:[DIC]],"=2"))/(COUNTA(PlanTrabajo4[[#This Row],[ENE]:[DIC]]))) -> 0 | AA31: Tema habilitación
A32: INTERVENCION DEL RIESGO | B32: RIESGO LOCATIVO | C32: Caídas a nivel/oden y aseo | D32: PROGRAMA DE GESTION/REQUISITO LEGAL/HABILITACION | E32: Fortalecer en el personal la habilidad de identificar riesgos y peligros durante el desplazamiento por terrenos irregulares, promoviendo la importancia del orden y aseo en los sitios de trabajo, elementos distractores, tecnicas de desplazamiento con el fin de generar controles efectivos que permitan disminuir el riesgo de caídas a nivel. | F32: Identificar los riesgos asociados a caídas a nivel, presentes durante el desplazamiento por superficies irregulares, húmedas, desordenadas o mal señalizadas. Reconocer los peligros generados por la falta de orden y aseo, como materiales mal ubicados, residuos, cables, material vegetal, , herramientas en las áreas de tránsito y uso de elementos distractores como el celular. Desarrollar una actitud preventiva frente a las condiciones del entorno, anticipándose a situaciones que puedan causar caídas. Técncias basicas para desplazamiento por terrenos irregulares Aplicar acciones de control relacionadas con el orden, el aseo y la señalización adecuada de los sitios de trabajo. Promover el autocuidado y el cuidado colectivo, entendiendo que el orden y el aseo y evitar elementos distractores son responsabilidad de todos. | G32: 2 | H32: Magistral interactiva con el trabajador | I32: Evaluación escrita con calificación | J32: Registro de asistencia, evaluacion y/o certificado | K32: Todos los trabajadores asociado al contrato | L32: ESSA EPM Servicios de mantenimiento de líneas de transmisión de energía CW261422 | M32: ARL SURA/COORDINADOR HSEQ | T32: 1 | Z32: =IF(COUNTA(PlanTrabajo4[[#This Row],[ENE]:[DIC]])=0," ",(COUNTIF(PlanTrabajo4[[#This Row],[ENE]:[DIC]],"=2"))/(COUNTA(PlanTrabajo4[[#This Row],[ENE]:[DIC]]))) -> 0
A33: INTERVENCION DEL RIESGO | B33: RIESGO BIOLOGICO | C33: Técnicas de atención básica de emergencias por evento ambiental y acidente biològico | D33: PROGRAMA DE GESTION/REQUISITO LEGAL/HABILITACION | E33: Dar a conocer al personal técnicas básicas para la atención inicial de emergencias derivadas de eventos ambientales (derrames de sustancias químicas) y accidentes biológicos, con el fin de reducir el impacto en la salud, el ambiente y la seguridad, mientras se activa el protocolo de emergencia correspondiente. | F33: Identificar situaciones de emergencia ambiental y biológica que puedan presentarse durante el desarrollo de las actividades laborales. Reconocer las acciones iniciales seguras ante un derrame de sustancias químicas, evitando la exposición y la contaminación ambiental. Aplicar medidas básicas de atención en caso de mordedura de serpiente o picadura de animales peligrosos. Actuar de forma segura ante el contacto con plantas urticantes o venenosas, minimizando reacciones adversas. Fortalecer la toma de decisiones bajo situaciones de emergencia, priorizando la autoprotección y la activación de los canales de reporte y atención. | G33: 2 | H33: Magistral interactiva con el trabajador | I33: Evaluación escrita con calificación | J33: Registro de asistencia, evaluacion y/o certificado | K33: Todos los trabajadores asociado al contrato | L33: ESSA EPM Servicios de mantenimiento de líneas de transmisión de energía CW261422 | M33: ARL SURA/COORDINADOR HSEQ | T33: 1 | Z33: =IF(COUNTA(PlanTrabajo4[[#This Row],[ENE]:[DIC]])=0," ",(COUNTIF(PlanTrabajo4[[#This Row],[ENE]:[DIC]],"=2"))/(COUNTA(PlanTrabajo4[[#This Row],[ENE]:[DIC]]))) -> 0
A34: PLAN DE EMERGENCIAS | B34: PLAN DE EMERGENCIAS | C34: Primeros auxilios - evacuaciòn y camillaje (Técnicas de atención básica método PAS ( proteger, avisar, socorrer) | D34: PROGRAMA DE GESTION/REQUISITO LEGAL/HABILITACION | E34: Dar a conocer a los trabajadores las actuaciones y técnicas básicas de primeros auxilios, evacuación y camillaje, aplicando el método PAS, que permitan la atención inmediata y segura de un lesionado que se encuentre en situación de riesgo, hasta la llegada de personal especializado. | F34: Reconocer situaciones de emergencia que requieran atención inmediata por accidentes asociados a riesgo de alturas, eléctrico, locativo y mecánico. Aplicar correctamente el método PAS (Proteger, Avisar, Socorrer) como base de la atención inicial de emergencias. Actuar de forma segura para proteger la escena y al lesionado, evitando riesgos adicionales para el rescatista y la víctima. Ejecutar técnicas básicas de primeros auxilios, priorizando la atención inicial del lesionado. Conocer técnicas seguras de evacuación y camillaje, de acuerdo con el tipo de lesión y el entorno del accidente. | G34: 3 | H34: Teorico- Practico | I34: Taller practico y/o taller | J34: Registro de asistencia, evaluacion y/o certificado | K34: Todos los trabajadores asociado al contrato | L34: ESSA EPM Servicios de mantenimiento de líneas de transmisión de energía CW261422 | M34: ARL SURA/COORDINADOR HSEQ | T34: 1 | Z34: =IF(COUNTA(PlanTrabajo4[[#This Row],[ENE]:[DIC]])=0," ",(COUNTIF(PlanTrabajo4[[#This Row],[ENE]:[DIC]],"=2"))/(COUNTA(PlanTrabajo4[[#This Row],[ENE]:[DIC]]))) -> 0 | AA34: Tema habilitación
A35: INTERVENCION DEL RIESGO | B35: PROGRAMA DE RIESGO PSICOSOCIAL | C35: Tecnicas de asertividad: Comunicación Asertiva – Técnicas Asertivas – Habilidades Sociales. | D35: Accidentalidad | E35: Fortalecer en los trabajadores las habilidades sociales y de comunicación asertiva, que les permitan crear vínculos positivos, mejorar la convivencia laboral y facilitar el compromiso colectivo con la seguridad y el autocuidado, contribuyendo a la prevención de accidentes asociados a riesgos locativos y mecánicos. | F35: Comprender el concepto de asertividad y su importancia en las relaciones laborales seguras. Diferenciar los estilos de comunicación (pasivo, agresivo y asertivo) y su impacto en la seguridad. Aplicar técnicas de comunicación asertiva, favoreciendo el diálogo respetuoso y constructivo frente a situaciones de riesgo. Desarrollar habilidades sociales que promuevan el trabajo en equipo, la cooperación y el apoyo mutuo. Facilitar la identificación y comunicación de riesgos locativos y mecánicos, promoviendo el autocuidado y el cuidado de los compañeros. | G35: 2 | H35: Magistral interactiva con el trabajador | I35: Evaluación escrita con calificación | J35: Registro de asistencia, evaluacion y/o certificado | K35: Todos los trabajadores asociado al contrato | L35: ESSA EPM Servicios de mantenimiento de líneas de transmisión de energía CW261422 | M35: ARL SURA/COORDINADOR HSEQ | T35: 1 | Z35: =IF(COUNTA(PlanTrabajo4[[#This Row],[ENE]:[DIC]])=0," ",(COUNTIF(PlanTrabajo4[[#This Row],[ENE]:[DIC]],"=2"))/(COUNTA(PlanTrabajo4[[#This Row],[ENE]:[DIC]]))) -> 0 | AA35: Tema habilitación
A36: INTERVENCION DEL RIESGO | B36: GESTIÓN DEL RIESGOS PRIORITARIOS | C36: Toma de decisiónes y resolución de problemas en la gestión de los riesgos en el trabajo | D36: PROGRAMA DE GESTION/REQUISITO LEGAL/HABILITACION | E36: Brindar a los trabajadores herramientas para la toma de decisiones seguras y la resolución efectiva de problemas, fortaleciendo la evaluación de riesgos en tiempo real mediante el pensamiento crítico, con el fin de minimizar errores humanos y prevenir accidentes de trabajo. | F36: Reconocer la importancia de la toma de decisiones en la gestión del riesgo, especialmente en actividades críticas del trabajo diario. Aplicar técnicas de evaluación de riesgos en tiempo real, identificando peligros antes y durante la ejecución de las tareas. Desarrollar el pensamiento crítico, analizando situaciones laborales y anticipando posibles consecuencias. Identificar factores que favorecen el error humano, tales como la prisa, el exceso de confianza, la rutina y la distracción. Implementar estrategias prácticas para minimizar errores humanos, promoviendo decisiones seguras y responsables. | G36: 2 | H36: Magistral interactiva con el trabajador | I36: Evaluación escrita con calificación | J36: Registro de asistencia, evaluacion y/o certificado | K36: Todos los trabajadores asociado al contrato | L36: ESSA EPM Servicios de mantenimiento de líneas de transmisión de energía CW261422 | M36: ARL SURA/COORDINADOR HSEQ | U36: 1 | Z36: =IF(COUNTA(PlanTrabajo4[[#This Row],[ENE]:[DIC]])=0," ",(COUNTIF(PlanTrabajo4[[#This Row],[ENE]:[DIC]],"=2"))/(COUNTA(PlanTrabajo4[[#This Row],[ENE]:[DIC]]))) -> 0 | AA36: Tema habilitación
A37: INTERVENCION DEL RIESGO | B37: PLAN ESTRATEGICO DE SEGURIDAD VIAL | C37: Desplazamientos seguros en la vía/seguridad vial pasajeros/seguridad vial a peatones | D37: PROGRAMA DE GESTION/REQUISITO LEGAL/HABILITACION/MATRIZ DE PELIGROS | E37: Dar a conocer a los trabajadores buenas prácticas y conductas seguras de movilidad, promoviendo el respeto de los roles en la vía, el cumplimiento de la normatividad de tránsito y la identificación de factores de riesgo, con el fin de prevenir incidentes y accidentes viales durante los desplazamientos laborales y personales. | F37: Reconocer los diferentes roles en la vía (peatón, pasajero, conductor) y sus responsabilidades en la seguridad vial. Adoptar comportamientos seguros durante los desplazamientos, tanto en condición de peatón como de pasajero. Fomentar el respeto por los demás actores viales, promoviendo una convivencia responsable y preventiva en la vía. Conocer y aplicar la normatividad básica de tránsito, como parte del autocuidado y la cultura vial. Identificar los factores de riesgo más comunes en la vía, que incrementan la probabilidad de incidentes y accidentes. | G37: 2 | H37: Magistral interactiva con el trabajador | I37: Evaluación escrita con calificación | J37: Registro de asistencia, evaluacion y/o certificado | K37: Todos los trabajadores asociado al contrato | L37: ESSA EPM Servicios de mantenimiento de líneas de transmisión de energía CW261422 | M37: ARL SURA/COORDINADOR HSEQ | U37: 1 | Z37: =IF(COUNTA(PlanTrabajo4[[#This Row],[ENE]:[DIC]])=0," ",(COUNTIF(PlanTrabajo4[[#This Row],[ENE]:[DIC]],"=2"))/(COUNTA(PlanTrabajo4[[#This Row],[ENE]:[DIC]]))) -> 0
A38: INTERVENCION DEL RIESGO | B38: RIESGO MECANICO | C38: Riesgo de golpes por o contra objetos ( incluye caida de objetos ( altura), en almacenamiento de elementos, desplazamiento de materiales en terrenos inclinados e irregulares etc. | D38: PROGRAMA DE GESTION/REQUISITO LEGAL/HABILITACION/MATRIZ DE PELIGROS | E38: Dar a conocer a los trabajadores las medidas de seguridad necesarias para prevenir accidentes por golpes de o contra objetos, durante actividades con riesgo de caída de objetos desde altura, almacenamiento de elementos y manipulación y desplazamiento de materiales en terrenos regulares o irregulares, contribuyendo a la reducción de accidentes en el mantenimiento de líneas de transmisión. | F38: Identificar los riesgos asociados a golpes por o contra objetos, presentes en las actividades de mantenimiento de líneas de transmisión. Reconocer situaciones con riesgo de caída de objetos desde altura, derivadas del trabajo en estructuras, torres y postes. Aplicar medidas de seguridad durante el almacenamiento de materiales y herramientas, evitando desplazamientos o caídas inesperadas. Implementar prácticas seguras para la manipulación y traslado de materiales en terrenos inclinados, irregulares o de difícil acceso. Fomentar el uso adecuado de elementos de protección personal (EPP) como medida preventiva frente a impactos y golpes. Promover una actitud preventiva y de autocuidado, fortaleciendo la cultura de seguridad en actividades críticas. | G38: 2 | H38: Magistral interactiva con el trabajador | I38: Evaluación escrita con calificación | J38: Registro de asistencia, evaluacion y/o certificado | K38: Todos los trabajadores asociado al contrato | L38: ESSA EPM Servicios de mantenimiento de líneas de transmisión de energía CW261422 | M38: ARL SURA/COORDINADOR HSEQ | U38: 1 | Z38: =IF(COUNTA(PlanTrabajo4[[#This Row],[ENE]:[DIC]])=0," ",(COUNTIF(PlanTrabajo4[[#This Row],[ENE]:[DIC]],"=2"))/(COUNTA(PlanTrabajo4[[#This Row],[ENE]:[DIC]]))) -> 0
A39: INTERVENCION DEL RIESGO | B39: RIESGO BIOLOGICO | C39: Riesgo biologico : Bacterias, virus y hongos /Vegetación urticante, venenosa o punzante/ animales venenosos (serpientes, arañas, escorpiones, avispas, abejas) | D39: CONTROL DE ACCIDENTALIDAD / PROGRAMA DE GESTION | E39: Dar recomendaciones de seguridad y medidas preventivas al personal para la identificación y el manejo seguro del riesgo biológico, incluyendo la exposición a bacterias, virus, hongos, vegetación urticante, venenosa o punzante y animales venenosos, con el fin de prevenir enfermedades, accidentes e impactos en la salud de los trabajadores. | F39: Identificar los principales riesgos biológicos a los que pueden estar expuestos durante el desarrollo de sus actividades laborales. Reconocer la vegetación urticante, venenosa o punzante, y adoptar medidas preventivas para evitar el contacto. Identificar animales venenosos o potencialmente peligrosos (serpientes, arañas, escorpiones, avispas, abejas) y aplicar comportamientos seguros. Aplicar medidas de prevención ante posibles contagios de enfermedades infectocontagiosas, reduciendo la exposición y transmisión. Conocer las recomendaciones básicas de actuación ante un contacto o exposición a un riesgo biológico. | G39: 2 | H39: Magistral interactiva con el trabajador | I39: Evaluación escrita con calificación | J39: Registro de asistencia, evaluacion y/o certificado | K39: Todos los trabajadores asociado al contrato | L39: ESSA EPM Servicios de mantenimiento de líneas de transmisión de energía CW261422 | M39: ARL SURA/COORDINADOR HSEQ | U39: 1 | Z39: =IF(COUNTA(PlanTrabajo4[[#This Row],[ENE]:[DIC]])=0," ",(COUNTIF(PlanTrabajo4[[#This Row],[ENE]:[DIC]],"=2"))/(COUNTA(PlanTrabajo4[[#This Row],[ENE]:[DIC]]))) -> 0
A40: INTERVENCION DEL RIESGO | B40: PROGRAMA DE GESTION DE RIESGO RUIDO | C40: Riesgo auditivo | D40: PROGRAMA DE GESTION/MATRIZ DE PELIGROS | E40: Dar a conocer a los trabajadores el riesgo asociado a la exposición al ruido, sus efectos en la salud auditiva, así como los cuidados y controles a implementar, con el fin de prevenir la pérdida de la audición y promover el autocuidado en el entorno laboral. | F40: Identificar el riesgo auditivo derivado de la exposición a fuentes de ruido presentes en el desarrollo de sus actividades. Reconocer los efectos del ruido en la salud, incluyendo la pérdida auditiva temporal o permanente. Conocer los límites de exposición al ruido y la importancia de su control. Aplicar medidas de prevención y control, enfocadas en la reducción del ruido y la protección de la audición. Utilizar correctamente los elementos de protección auditiva, garantizando su eficacia. Promover hábitos de autocuidado auditivo, dentro y fuera del entorno laboral. | G40: 2 | H40: Magistral interactiva con el trabajador | I40: Evaluación escrita con calificación | J40: Registro de asistencia, evaluacion y/o certificado | K40: Todos los trabajadores asociado al contrato | L40: ESSA EPM Servicios de mantenimiento de líneas de transmisión de energía CW261422 | M40: ARL SURA/COORDINADOR HSEQ | U40: 1 | Z40: =IF(COUNTA(PlanTrabajo4[[#This Row],[ENE]:[DIC]])=0," ",(COUNTIF(PlanTrabajo4[[#This Row],[ENE]:[DIC]],"=2"))/(COUNTA(PlanTrabajo4[[#This Row],[ENE]:[DIC]]))) -> 0
A41: INTERVENCION DEL RIESGO | B41: PROGRAMA DE SVE OSTEOMUSCULAR | C41: Pausas activas/ calistenias/ higiene postural | D41: CONTROL DE ACCIDENTALIDAD / PROGRAMA DE GESTION/MATRIZ DE PELIGROS | E41: Dar a conocer a los trabajadores la importancia de la higiene postural, las pausas activas y la calistenia, mediante la aplicación de técnicas y ejercicios preventivos, con el fin de disminuir la fatiga laboral y prevenir trastornos osteomusculares, promoviendo el bienestar y el desempeño seguro en el trabajo. | F41: Reconocer la importancia de la higiene postural durante la ejecución de las actividades laborales, tanto estáticas como dinámicas. Identificar los riesgos ergonómicos asociados a malas posturas, movimientos repetitivos y sobreesfuerzos. Aplicar pausas activas como estrategia preventiva para reducir la fatiga física y mental. Realizar ejercicios de calistenia y estiramiento, contribuyendo a la movilidad, flexibilidad y fortalecimiento muscular. Promover el autocuidado físico, integrando hábitos saludables a la rutina laboral diaria. | G41: 2 | H41: Teorico- Practico | I41: Evaluacion Oral/ | J41: Taller practico y/o taller/evaluyacion | K41: Todos los trabajadores asociado al contrato | L41: ESSA EPM Servicios de mantenimiento de líneas de transmisión de energía CW261422 | M41: ARL SURA/COORDINADOR HSEQ | V41: 1 | Z41: =IF(COUNTA(PlanTrabajo4[[#This Row],[ENE]:[DIC]])=0," ",(COUNTIF(PlanTrabajo4[[#This Row],[ENE]:[DIC]],"=2"))/(COUNTA(PlanTrabajo4[[#This Row],[ENE]:[DIC]]))) -> 0
A42: INTERVENCION DEL RIESGO | B42: PROGRAMA ESTILOS DE VIDA SALUDABLE | C42: Prevenciòn del riesgo cardiovascular y otras enfermedades | D42: PROGRAMA DE GESTION/MATRIZ DE PELIGROS | E42: Informar y concienciar a los trabajadores sobre la importancia de los estilos de vida saludables en la prevención y el control de las enfermedades cardiovasculares y otras enfermedades crónicas, promoviendo el autocuidado, la salud integral y la reducción de factores de riesgo asociados al trabajo y a la vida cotidiana. | F42: Reconocer los principales factores de riesgo cardiovascular, asociados a hábitos de vida no saludables. Identificar las enfermedades crónicas más frecuentes, tales como diabetes mellitus, hipertensión arterial, enfermedad pulmonar obstructiva crónica (EPOC), accidente cerebrovascular (ACV), obesidad, enfermedad hepática y trastornos derivados de la mala nutrición. Comprender la relación entre los estilos de vida y la salud, destacando el impacto del sedentarismo, la alimentación inadecuada, el consumo de alcohol, el tabaquismo y el estrés. Promover hábitos saludables, orientados a la prevención y control de enfermedades crónicas. Fomentar la responsabilidad individual frente al autocuidado y el seguimiento médico preventivo | G42: 2 | H42: Magistral interactiva con el trabajador | I42: Evaluación escrita con calificación | J42: Registro de asistencia, evaluacion y/o certificado | K42: Todos los trabajadores asociado al contrato | L42: ESSA EPM Servicios de mantenimiento de líneas de transmisión de energía CW261422 | M42: ARL SURA/COORDINADOR HSEQ | V42: 1 | Z42: =IF(COUNTA(PlanTrabajo4[[#This Row],[ENE]:[DIC]])=0," ",(COUNTIF(PlanTrabajo4[[#This Row],[ENE]:[DIC]],"=2"))/(COUNTA(PlanTrabajo4[[#This Row],[ENE]:[DIC]]))) -> 0
A43: INTERVENCION DEL RIESGO | B43: PROMOCION Y PREVENCIÓN | C43: Cuidado visual | D43: PROGRAMA DE GESTION/MATRIZ DE PELIGROS | E43: Promover el cuidado de la salud visual de los trabajadores mediante la identificación de riesgos que afectan la visión, la adopción de hábitos visuales saludables y el uso adecuado de protección visual, con el fin de prevenir enfermedades, fatiga visual y accidentes en el entorno laboral y extralaboral. | F43: Reconocer los factores de riesgo visual presentes en su puesto de trabajo. Identificar síntomas de fatiga visual y alteraciones de la visión. Aplicar buenas prácticas de cuidado visual, especialmente frente a pantallas, iluminación y tareas de precisión. Utilizar de manera correcta los elementos de protección visual según la actividad desempeñada. Adoptar hábitos preventivos para disminuir el cansancio visual y proteger la salud ocular. Comprender la importancia de los controles médicos visuales periódicos. Contribuir a un ambiente de trabajo más seguro y saludable mediante el autocuidado visual. | G43: 2 | H43: Magistral interactiva con el trabajador | I43: Evaluación escrita con calificación | J43: Registro de asistencia, evaluacion y/o certificado | K43: Todos los trabajadores asociado al contrato | L43: ESSA EPM Servicios de mantenimiento de líneas de transmisión de energía CW261422 | M43: ARL SURA/COORDINADOR HSEQ | V43: 1 | Z43: =IF(COUNTA(PlanTrabajo4[[#This Row],[ENE]:[DIC]])=0," ",(COUNTIF(PlanTrabajo4[[#This Row],[ENE]:[DIC]],"=2"))/(COUNTA(PlanTrabajo4[[#This Row],[ENE]:[DIC]]))) -> 0
A44: INTERVENCION DEL RIESGO | B44: PROGRAMA DE SVE OSTEOMUSCULAR | C44: Manipulación y tansporte de cargas, posturas y trabajo repetitivo | D44: CONTROL DE ACCIDENTALIDAD / PROGRAMA DE GESTION/MATRIZ DE PELIGROS | E44: Brindar herramientas prácticas a los trabajadores que les permitan reconocer, aplicar y mantener técnicas seguras en la manipulación y transporte de cargas, así como medidas preventivas frente a posturas forzadas, estáticas, prolongadas y trabajos repetitivos, con el fin de prevenir y controlar trastornos osteomusculares. | F44: Reconocer los riesgos osteomusculares asociados a la manipulación de cargas, posturas inadecuadas y tareas repetitivas. Aplicar correctamente técnicas seguras de manipulación y transporte manual de cargas. Identificar posturas forzadas, estáticas y prolongadas, y adoptar posturas ergonómicas adecuadas. Implementar medidas preventivas durante trabajos repetitivos. Participar activamente en la prevención de lesiones musculoesqueléticas en su puesto de trabajo. | G44: 2 | H44: Taller Teorico- Practico | I44: Evaluación escrita con calificación | J44: Registro de asistencia, evaluacion y/o certificado | K44: Todos los trabajadores asociado al contrato | L44: ESSA EPM Servicios de mantenimiento de líneas de transmisión de energía CW261422 | M44: ARL SURA/COORDINADOR HSEQ | V44: 1 | Z44: =IF(COUNTA(PlanTrabajo4[[#This Row],[ENE]:[DIC]])=0," ",(COUNTIF(PlanTrabajo4[[#This Row],[ENE]:[DIC]],"=2"))/(COUNTA(PlanTrabajo4[[#This Row],[ENE]:[DIC]]))) -> 0
A45: INTERVENCION DEL RIESGO | B45: CONDICIONES DE SEGURIDAD/INSPECCIONES | C45: Señalizacion y tipos de señalizacion: Inspecciones ( formatos y correcto diligenciamiento) | D45: MATRIZ DE PELIGROS | E45: Proporcionar a los trabajadores los conocimientos básicos y prácticos sobre señalización de seguridad y la realización de inspecciones de seguridad, que les permitan identificar los riesgos presentes en las diferentes áreas de la empresa, utilizar correctamente los formatos de inspección, y apoyar la implementación efectiva de las medidas de control. | F45: Reconocer la importancia de la señalización como medida preventiva. Identificar los tipos de señalización de seguridad y su correcta aplicación en el lugar de trabajo. Comprender qué es una inspección de seguridad y por qué es fundamental para la prevención de accidentes. Aplicar correctamente los formatos de inspección, diligenciándolos de forma clara y objetiva. Identificar actos y condiciones inseguras durante las inspecciones. Contribuir activamente en la propuesta y seguimiento de medidas de control. | G45: 2 | H45: Magistral interactiva con el trabajador | I45: Evaluación escrita con calificación | J45: Registro de asistencia, evaluacion y/o certificado | K45: Todos los trabajadores asociado al contrato | L45: ESSA EPM Servicios de mantenimiento de líneas de transmisión de energía CW261422 | M45: ARL SURA/COORDINADOR HSEQ | V45: 1 | Z45: =IF(COUNTA(PlanTrabajo4[[#This Row],[ENE]:[DIC]])=0," ",(COUNTIF(PlanTrabajo4[[#This Row],[ENE]:[DIC]],"=2"))/(COUNTA(PlanTrabajo4[[#This Row],[ENE]:[DIC]]))) -> 0
A46: INTERVENCION DEL RIESGO | B46: PLAN ESTRATEGICO DE SEGURIDAD VIAL | C46: Manejo Defensivo y Seguridad vial Vehículos Seguros y análisis de factores de riesgo en la vía. | D46: REQUISITO LEGAL | E46: Dar a conocer a los trabajadores buenas prácticas y conductas seguras de movilidad, basadas en la normatividad vigente en tránsito y transporte, que les permitan desempeñar de manera segura su rol en la seguridad vial (conductor, peatón, pasajero o ciclista), fortalecer el concepto de vehículos seguros y analizar los factores de riesgo presentes en la vía, contribuyendo a la prevención de accidentes, lesiones y fatalidades viales. | F46: Reconocer la importancia de la seguridad vial en el ámbito laboral y cotidiano. Identificar los roles de la seguridad vial y sus responsabilidades. Aplicar principios de manejo defensivo para anticiparse y evitar incidentes en la vía. Verificar condiciones de vehículos seguros antes y durante la conducción. Analizar los factores de riesgo viales (humanos, del vehículo y del entorno). Adoptar comportamientos seguros conforme a la normatividad vigente de tránsito y transporte. | G46: 2 | H46: Magistral interactiva con el trabajador | I46: Evaluación escrita con calificación | J46: Registro de asistencia, evaluacion y/o certificado | K46: Todos los trabajadores asociado al contrato | L46: ESSA EPM Servicios de mantenimiento de líneas de transmisión de energía CW261422 | M46: ARL SURA/COORDINADOR HSEQ | W46: 1 | Z46: =IF(COUNTA(PlanTrabajo4[[#This Row],[ENE]:[DIC]])=0," ",(COUNTIF(PlanTrabajo4[[#This Row],[ENE]:[DIC]],"=2"))/(COUNTA(PlanTrabajo4[[#This Row],[ENE]:[DIC]]))) -> 0
A47: INTERVENCION DEL RIESGO | B47: PROGRAMA DE RIESGO PSICOSOCIAL | C47: Sinergia positiva | D47: CONTROL DE ACCIDENTALIDAD / PROGRAMA DE GESTION/MATRIZ DE PELIGROS | E47: Fortalecer en los colaboradores las habilidades necesarias para generar sinergia positiva,desarrollando las 5 C del trabajo en equipo (Comunicación.,Coordinación.Complementariedad, Confianza, Compromiso con cumplimiento normas de seguridad) , reconociendo los tipos de sinergia y mejorando la toma de decisiones, con el fin de potenciar el trabajo conjunto, el compromiso colectivo y el cumplimiento de las normas de seguridad. | F47: Diferenciar un grupo de trabajo de un equipo de trabajo. Comprender el concepto de sinergia positiva y su impacto en los resultados. Fortalecer las 5 C del trabajo en equipo enfocado en seguridad. Identificar los tipos de sinergia y su presencia en el entorno laboral. Desarrollar habilidades básicas para la toma de decisiones en equipo. Promover el compromiso individual y colectivo con las normas de seguridad y los objetivos comunes. | G47: 2 | H47: Magistral interactiva con el trabajador | I47: Evaluación escrita con calificación | J47: Registro de asistencia, evaluacion y/o certificado | K47: Todos los trabajadores asociado al contrato | L47: ESSA EPM Servicios de mantenimiento de líneas de transmisión de energía CW261422 | M47: ARL SURA/COORDINADOR HSEQ | W47: 1 | Z47: =IF(COUNTA(PlanTrabajo4[[#This Row],[ENE]:[DIC]])=0," ",(COUNTIF(PlanTrabajo4[[#This Row],[ENE]:[DIC]],"=2"))/(COUNTA(PlanTrabajo4[[#This Row],[ENE]:[DIC]]))) -> 0 | AA47: Tema habilitación
A48: INTERVENCION DEL RIESGO | B48: PROGRAMA DE GESTION DE RIESGO RUIDO | C48: Funcionamiento auditivo/Uso higiene protección auditiva | D48: PROGRAMA DE GESTION/MATRIZ DE PELIGROS | E48: Capacitar al personal sobre el funcionamiento del oído humano, su anatomía y cuidado, así como la importancia del uso correcto, mantenimiento e higiene de los protectores auditivos, con el fin de prevenir daños auditivos, promover el autocuidado y fortalecer la cultura de seguridad y salud en el trabajo. | F48: Comprender el funcionamiento del sistema auditivo y cómo se produce la audición. Identificar la anatomía del oído (oído externo, medio e interno). Reconocer los efectos del ruido sobre la audición y la salud. Aplicar buenas prácticas para el cuidado del oído. Usar correctamente los protectores auditivos según el tipo de riesgo. Realizar una adecuada limpieza, almacenamiento e higiene de la protección auditiva. | G48: 2 | H48: Magistral interactiva con el trabajador | I48: Evaluación escrita con calificación | J48: Registro de asistencia, evaluacion y/o certificado | K48: Todos los trabajadores asociado al contrato | L48: ESSA EPM Servicios de mantenimiento de líneas de transmisión de energía CW261422 | M48: ARL SURA/COORDINADOR HSEQ | W48: 1 | Z48: =IF(COUNTA(PlanTrabajo4[[#This Row],[ENE]:[DIC]])=0," ",(COUNTIF(PlanTrabajo4[[#This Row],[ENE]:[DIC]],"=2"))/(COUNTA(PlanTrabajo4[[#This Row],[ENE]:[DIC]]))) -> 0
A49: INTERVENCION DEL RIESGO | B49: PROGRAMA ESTILOS DE VIDA SALUDABLE | C49: Importancia de ejercicio y alimentaciòn sana-saludable | D49: PROGRAMA DE GESTION/MATRIZ DE PELIGROS | E49: Dar a conocer a los trabajadores la importancia de la alimentación sana y la actividad física regular como pilares fundamentales de un estilo de vida saludable, destacando su impacto positivo en el sistema inmunológico, la salud física y mental, el desempeño laboral y la calidad de vida, tanto dentro como fuera del entorno laboral. | F49: Reconocer los beneficios de una alimentación equilibrada y la actividad física para la salud integral. Comprender cómo el ejercicio y una dieta saludable fortalecen el sistema inmunológico. Identificar hábitos alimenticios saludables aplicables a la rutina laboral y diaria. Conocer recomendaciones básicas de actividad física de acuerdo con su condición y tipo de trabajo. Adoptar prácticas de autocuidado que contribuyan a la prevención de enfermedades y al mejoramiento de la calidad de vida. | G49: 2 | H49: Magistral interactiva con el trabajador | I49: Evaluación escrita con calificación | J49: Registro de asistencia, evaluacion y/o certificado | K49: Todos los trabajadores asociado al contrato | L49: ESSA EPM Servicios de mantenimiento de líneas de transmisión de energía CW261422 | M49: ARL SURA/COORDINADOR HSEQ | W49: 1 | Z49: =IF(COUNTA(PlanTrabajo4[[#This Row],[ENE]:[DIC]])=0," ",(COUNTIF(PlanTrabajo4[[#This Row],[ENE]:[DIC]],"=2"))/(COUNTA(PlanTrabajo4[[#This Row],[ENE]:[DIC]]))) -> 0
A50: INTERVENCIÒN DEL RIESGO / PLAN DE EMERGENCIAS | B50: PROGRAMA DE GESTIÓN PARA EL RIESGO ELÉCTRICO / PLAN DE EMERGENCIAS | C50: Gestión de emergencias primeros auxilios en pacientes por riesgo eléctrico | D50: CONTROL DE ACCIDENTALIDAD / PROGRAMA DE GESTION/MATRIZ DE PELIGROS | E50: Capacitar a los trabajadores en la gestión de emergencias y atención en primeros auxilios frente a accidentes por riesgo eléctrico, proporcionando los conocimientos básicos y procedimientos seguros para la atención inicial del electrocutado y manejo de quemaduras, con el fin de reducir la gravedad de las lesiones, prevenir complicaciones y salvar vidas como parte de la atención previa a la médica especializada. | F50: Reconocer una emergencia por riesgo eléctrico y actuar de forma segura. Identificar los efectos de una descarga eléctrica en el cuerpo humano. Aplicar los protocolos básicos de primeros auxilios al electrocutado. Reconocer y atender quemaduras eléctricas, evitando errores comunes. Activar correctamente la cadena de atención de emergencias. Proteger su propia integridad durante la atención de la emergencia. | G50: 2 | H50: Teórico - práctica | I50: Evaluación escrita con calificación | J50: Registro de asistencia, evaluacion y/o certificado | K50: Todos los trabajadores asociado al contrato | L50: ESSA EPM Servicios de mantenimiento de líneas de transmisión de energía CW261422 | M50: ARL SURA/COORDINADOR HSEQ | X50: 1 | Z50: =IF(COUNTA(PlanTrabajo4[[#This Row],[ENE]:[DIC]])=0," ",(COUNTIF(PlanTrabajo4[[#This Row],[ENE]:[DIC]],"=2"))/(COUNTA(PlanTrabajo4[[#This Row],[ENE]:[DIC]]))) -> 0 | AA50: Tema habilitación(AD)
A51: INTERVENCION DEL RIESGO | B51: RIESGO MECANICO | C51: Manipulacion de herramientas de corte ( machete, motosierra, guadañadoras, podadoras alturas y otra herramientas de corte) | D51: CONTROL DE ACCIDENTALIDAD / PROGRAMA DE GESTION/MATRIZ DE PELIGROS | E51: Fortalecer en los trabajadores las conductas seguras en la manipulación de herramientas de corte, promoviendo la correcta elección, uso, inspección y mantenimiento de las mismas, de acuerdo con la actividad a ejecutar, con el fin de prevenir accidentes de trabajo, lesiones graves y daños a equipos. | F51: Identificar los riesgos asociados al uso de herramientas de corte. Seleccionar la herramienta adecuada según la actividad y el entorno. Aplicar técnicas seguras de uso, transporte y almacenamiento. Reconocer y corregir actos y condiciones inseguras. Usar correctamente los Elementos de Protección Personal (EPP). Realizar inspecciones básicas y mantenimiento preventivo. | G51: 3 | H51: Taller Teorico- Practico | I51: Evaluación escrita con calificación | J51: Registro de asistencia, evaluacion y/o certificado | K51: Todos los trabajadores asociado al contrato | L51: ESSA EPM Servicios de mantenimiento de líneas de transmisión de energía CW261422 | M51: ARL SURA/COORDINADOR HSEQ | X51: 1 | Z51: =IF(COUNTA(PlanTrabajo4[[#This Row],[ENE]:[DIC]])=0," ",(COUNTIF(PlanTrabajo4[[#This Row],[ENE]:[DIC]],"=2"))/(COUNTA(PlanTrabajo4[[#This Row],[ENE]:[DIC]]))) -> 0 | AA51: Tema habilitación
A52: INTERVENCION DEL RIESGO | B52: PROGRAMA DE RIESGO PSICOSOCIAL | C52: Gestión para el cuidado integral de la salud de los trabajadores ( prevención de estrés,depresión,ansiedad) | D52: PROGRAMA DE GESTION/MATRIZ DE PELIGROS | E52: Brindar a los trabajadores herramientas prácticas para la prevención y manejo del estrés, la ansiedad y la depresión, mediante el reconocimiento de los factores de riesgo psicosocial, promoviendo el autocuidado, el equilibrio emocional y el bienestar integral, que favorezca el desempeño laboral y la calidad de vida en los entornos laboral y personal. | F52: Comprender qué son los factores de riesgo psicosocial y su impacto en la salud. Identificar signos tempranos de estrés, ansiedad y depresión. Reconocer factores psicosociales presentes en el trabajo y la vida cotidiana. Aplicar estrategias prácticas de prevención y manejo emocional. Fortalecer habilidades de autocuidado, comunicación y afrontamiento. Conocer cuándo y cómo buscar apoyo oportuno. | G52: 2 | H52: Magistral interactiva con el trabajador | I52: Evaluación escrita con calificación | J52: Registro de asistencia, evaluacion y/o certificado | K52: Todos los trabajadores asociado al contrato | L52: ESSA EPM Servicios de mantenimiento de líneas de transmisión de energía CW261422 | M52: ARL SURA/COORDINADOR HSEQ | X52: 1 | Z52: =IF(COUNTA(PlanTrabajo4[[#This Row],[ENE]:[DIC]])=0," ",(COUNTIF(PlanTrabajo4[[#This Row],[ENE]:[DIC]],"=2"))/(COUNTA(PlanTrabajo4[[#This Row],[ENE]:[DIC]]))) -> 0
A53: ISO 900:2015 | B53: CALIDAD | C53: Sistema de Gestión de la Calidad | D53: ISO 9001 | E53: Capacitar al personal en los principios, requisitos y responsabilidades establecidos en la Norma ISO 9001:2015, promoviendo la comprensión del Sistema de Gestión de la Calidad, la mejora continua y la orientación al cliente, asegurando la correcta aplicación de los procesos y el cumplimiento organizacional. | F53: Comprender qué es la ISO 9001 y para qué sirve Reconocer su rol y responsabilidad dentro del Sistema de Gestión Aplicar el enfoque basado en procesos y en riesgos Contribuir a la satisfacción del cliente Participar activamente en la mejora continua del SGC | G53: 2 | H53: Magistral interactiva con el trabajador | I53: Evaluación escrita con calificación | J53: Registro de asistencia, evaluacion y/o certificado | K53: Todos los trabajadores asociado al contrato | L53: ESSA EPM Servicios de mantenimiento de líneas de transmisión de energía CW261422 | M53: COODINADOR HSEQ | Y53: 1 | Z53: =IF(COUNTA(PlanTrabajo4[[#This Row],[ENE]:[DIC]])=0," ",(COUNTIF(PlanTrabajo4[[#This Row],[ENE]:[DIC]],"=2"))/(COUNTA(PlanTrabajo4[[#This Row],[ENE]:[DIC]]))) -> 0

Sheet m1
A1: OBJETIVO SGSST | B1: PROGRAMA | C1: ACTIVIDADES | D1: EVIDENCIA GENERADA | E1: CENTRO DE TRABAJO | F1: RESPONSABLES | G1: FECHA DE INICIO | H1: FECHA DE FIN | I1: % COMPLETADO | J1: Columna3 | K1: DURACION | L1: OBSERVACIONES Y SEGUIMIENTO | M1: Columna2
A2: CUMPLIMIENTO LEGAL | B2: POLITICAS (sgsst, psicoactivas, psicosocial) | C2: Revisiòn de politicas del sistema por parte de la gerencia y copasst, con actualización de fecha y publicación | D2: Acta de copasst donde evidencie divulgación politica, politica con fecha actualizada, firma de gerencia y publicada | I2: 0.25 | J2: ='PLAN CAP'!#REF! -> #REF! | K2: =IF(G4=" "," ",(_xlfn.DAYS(PlanTrabajo[[#This Row],[FECHA DE FIN]],PlanTrabajo[[#This Row],[FECHA DE INICIO]]))) -> 0
A3: MEJORA CONTINUA | B3: AUTODIAGNOSTICO RESOLUCIÒN 1111 DE 2017 | C3: Nombramiento de responsable del sistema, evidencia de perfil y competencia | D3: Acta firmada por la gerencia de nombramiento, curso 50 horas y licencia en salud ocupacional | G3: 43313 | H3: 43343 | I3: 0.25 | J3: ='PLAN CAP'!#REF! -> #REF! | K3: =IF(G5=" "," ",(_xlfn.DAYS(PlanTrabajo[[#This Row],[FECHA DE FIN]],PlanTrabajo[[#This Row],[FECHA DE INICIO]]))) -> 30
A4: MEJORA CONTINUA | B4: OBJETIVOS | C4: Revisión de objetivos e indicadores con metas para hacer ajustes según prioridades de la gerencia | D4: Matriz de objetivos e indicadores actualizada con nuevas metas | G4: 43101 | H4: 43130 | I4: 0.75 | J4: ='PLAN CAP'!#REF! -> #REF! | K4: =IF(G6=" "," ",(_xlfn.DAYS(PlanTrabajo[[#This Row],[FECHA DE FIN]],PlanTrabajo[[#This Row],[FECHA DE INICIO]]))) -> 29
A5: CUMPLIMIENTO LEGAL | B5: PLAN DE TRABAJO | C5: Establecer el plan de trabajo para el año, presentacion a la gerencia y al copasst | D5: Plan de trabajo con firma de gerencia, acta de copasst donde se evidencie presentación | I5: 1 | J5: ='PLAN CAP'!#REF! -> #REF! | K5: =IF(G7=" "," ",(_xlfn.DAYS(PlanTrabajo[[#This Row],[FECHA DE FIN]],PlanTrabajo[[#This Row],[FECHA DE INICIO]]))) -> 0
A6: FORMACION Y CAPACITACION | B6: PLAN DE CAPACITACIÓN | C6: Establecer plan de capacitación para el año validando que se contemplen todos los factores de riesgo de la matriz de peligros y presentarlo al copasst | D6: Plan de capacitación y acta de copasst donde se evidencia que se presenta | I6: 0.75 | J6: ='PLAN CAP'!#REF! -> #REF! | K6: =IF(G8=" "," ",(_xlfn.DAYS(PlanTrabajo[[#This Row],[FECHA DE FIN]],PlanTrabajo[[#This Row],[FECHA DE INICIO]]))) -> 0
A7: ASIGNAR RECURSOS | B7: PRESUPUESTO | C7: Establecer presupuesto del sistema contemplando recursos humanos, tecnicos y financieros, presentarlo a la gerencia para aval. | D7: Presupuesto del sistema firmado por la gerencia | I7: 1 | J7: ='PLAN CAP'!#REF! -> #REF! | K7: =IF(G9=" "," ",(_xlfn.DAYS(PlanTrabajo[[#This Row],[FECHA DE FIN]],PlanTrabajo[[#This Row],[FECHA DE INICIO]]))) -> 0
A8: MEJORA CONTINUA | B8: AUTODIAGNOSTICO RESOLUCIÒN 1111 DE 2017 | C8: Realizar autodiagnostico anual, ajustar plan de trabajo con los pendientes | D8: Autodiagnostico firmado por la gerencia, plan de trabajo ajustado con lo pendiente del autodiagnostico | I8: 0.75 | J8: ='PLAN CAP'!#REF! -> #REF! | K8: =IF(G10=" "," ",(_xlfn.DAYS(PlanTrabajo[[#This Row],[FECHA DE FIN]],PlanTrabajo[[#This Row],[FECHA DE INICIO]]))) -> 0
A9: CUMPLIMIENTO LEGAL | B9: ROLES Y RESPONSABILIDADES | C9: Entrega de perfil de responsabilidades de seguridad a todos los trabajadores de acuerdo a sus cargos | D9: Evidencia de recibido firmada por cada trabajador | I9: 0.5 | J9: ='PLAN CAP'!#REF! -> #REF! | K9: =IF(G11=" "," ",(_xlfn.DAYS(PlanTrabajo[[#This Row],[FECHA DE FIN]],PlanTrabajo[[#This Row],[FECHA DE INICIO]]))) -> 0
A10: FORMACION Y CAPACITACION | B10: PLAN DE CAPACITACIÓN | C10: Mantener actualizado el plan de capacitación con las actividades ejecutadas mes a mes | D10: Plan de capacitación actualizado y archivo de evidencias de capacitación | I10: 0.75 | J10: ='PLAN CAP'!#REF! -> #REF! | K10: =IF(G12=" "," ",(_xlfn.DAYS(PlanTrabajo[[#This Row],[FECHA DE FIN]],PlanTrabajo[[#This Row],[FECHA DE INICIO]]))) -> 0
A11: CUMPLIMIENTO LEGAL | B11: PLAN DE TRABAJO | C11: Mantener actualizado el plan de trabajo con las actividades ejecutadas mes a mes | D11: Plan de trabajo actualizado | I11: 0 | J11: ='PLAN CAP'!#REF! -> #REF! | K11: =IF(G13=" "," ",(_xlfn.DAYS(PlanTrabajo[[#This Row],[FECHA DE FIN]],PlanTrabajo[[#This Row],[FECHA DE INICIO]]))) -> 0
A12: CUMPLIMIENTO LEGAL | B12: MATRIZ DE REQUISITOS LEGALES | C12: Actualización de matriz de requisios legales | D12: Matriz de requisitos legales actualizada y divulgados los cambios | I12: 0.25 | J12: ='PLAN CAP'!#REF! -> #REF! | K12: =IF(G14=" "," ",(_xlfn.DAYS(PlanTrabajo[[#This Row],[FECHA DE FIN]],PlanTrabajo[[#This Row],[FECHA DE INICIO]]))) -> 0
A13: ASIGNAR RECURSOS | B13: PRESUPUESTO | C13: Actualización del presupuesto en su ejecución de acuerdo a los gastos contables | D13: Presupuesto actualizaado en su ejecución | J13: ='PLAN CAP'!#REF! -> #REF! | K13: =IF(G15=" "," ",(_xlfn.DAYS(PlanTrabajo[[#This Row],[FECHA DE FIN]],PlanTrabajo[[#This Row],[FECHA DE INICIO]]))) -> 0
A14: GESTION DEL RIESGO | B14: MATRIZ DE PELIGROS | C14: Actualizar la matriz de identificación de peligros, evaluación y valoración de riesgos | D14: Matriz de peligros actualizada | I14: 0.5 | J14: ='PLAN CAP'!#REF! -> #REF! | K14: =IF(G16=" "," ",(_xlfn.DAYS(PlanTrabajo[[#This Row],[FECHA DE FIN]],PlanTrabajo[[#This Row],[FECHA DE INICIO]]))) -> 0
A15: GESTION DEL RIESGO | B15: MATRIZ DE PELIGROS | C15: Taller de identificación de peligros con todos los trabajadores | D15: Registro de divulgaciòn a todos los trabajadores de los peligros y controles | I15: 1 | J15: ='PLAN CAP'!#REF! -> #REF! | K15: =IF(G17=" "," ",(_xlfn.DAYS(PlanTrabajo[[#This Row],[FECHA DE FIN]],PlanTrabajo[[#This Row],[FECHA DE INICIO]]))) -> 0
A16: CONTROL ACCIDENTALIDAD Y ENFERMEDAD | B16: PERFIL SOCIODEMOGRAFICO | C16: Actualizar la encuesta de perfil sociodemografico, tabulación y análisis de la información | D16: Perfil sociodemografico aplicado, tabulado y analizado | J16: ='PLAN CAP'!#REF! -> #REF! | K16: =IF(G18=" "," ",(_xlfn.DAYS(PlanTrabajo[[#This Row],[FECHA DE FIN]],PlanTrabajo[[#This Row],[FECHA DE INICIO]]))) -> 0
A17: CUMPLIMIENTO LEGAL | B17: COPASST | C17: Conformación del comité, validación que todos los integrantes estes vigentes | D17: Acta de conformación de copasst con evidencias de eleccción | J17: ='PLAN CAP'!#REF! -> #REF! | K17: =IF(G19=" "," ",(_xlfn.DAYS(PlanTrabajo[[#This Row],[FECHA DE FIN]],PlanTrabajo[[#This Row],[FECHA DE INICIO]]))) -> 0
A18: CUMPLIMIENTO LEGAL | B18: COPASST | C18: Capacitación al copasst en funciones, responsabiidades, investigacion de accidentes, inspecciones de seguridad | D18: Registro de capacitacion firmado por todos los integrantes del copasst con evidencia de evaluación | J18: ='PLAN CAP'!#REF! -> #REF! | K18: =IF(G20=" "," ",(_xlfn.DAYS(PlanTrabajo[[#This Row],[FECHA DE FIN]],PlanTrabajo[[#This Row],[FECHA DE INICIO]]))) -> 0
A19: CUMPLIMIENTO LEGAL | B19: COPASST | C19: Realizar plan de trabajo para año que contemple: inspecciones, investigación, revisión de plan de trabajo, revision de plan de capacitacion, revisión por la dirección, revisión de informes | D19: Plan de trabajo de copasst | J19: ='PLAN CAP'!#REF! -> #REF! | K19: =IF(G21=" "," ",(_xlfn.DAYS(PlanTrabajo[[#This Row],[FECHA DE FIN]],PlanTrabajo[[#This Row],[FECHA DE INICIO]]))) -> 0
A20: CUMPLIMIENTO LEGAL | B20: COPASST | C20: Inspecciones se seguridad realizadas con el copasst | D20: Registro de inspecciones realizadas por el copasst, evidencia de firma de los integrantes del copasst | J20: ='PLAN CAP'!#REF! -> #REF! | K20: =IF(G22=" "," ",(_xlfn.DAYS(PlanTrabajo[[#This Row],[FECHA DE FIN]],PlanTrabajo[[#This Row],[FECHA DE INICIO]]))) -> 0
A21: CUMPLIMIENTO LEGAL | B21: COPASST | C21: Reunión mensual de copasst con evidencia de cumplimiento de sus funciones | D21: Acta de reunión diligenciada con firmas | J21: ='PLAN CAP'!#REF! -> #REF! | K21: =IF(G23=" "," ",(_xlfn.DAYS(PlanTrabajo[[#This Row],[FECHA DE FIN]],PlanTrabajo[[#This Row],[FECHA DE INICIO]]))) -> 0
A22: CUMPLIMIENTO LEGAL | B22: COPASST | C22: Participación del comité en la planeación de la auditoria | D22: Plan de auditoria con firma del copasst | J22: ='PLAN CAP'!#REF! -> #REF! | K22: =IF(G24=" "," ",(_xlfn.DAYS(PlanTrabajo[[#This Row],[FECHA DE FIN]],PlanTrabajo[[#This Row],[FECHA DE INICIO]]))) -> 0
A23: CUMPLIMIENTO LEGAL | B23: COMITÉ DE CONVIVIENCIA LABORAL | C23: Conformación del comité, validación que todos los integrantes estes vigentes | D23: Acta de conformación del comité con soportes de elección | J23: ='PLAN CAP'!#REF! -> #REF! | K23: =IF(G25=" "," ",(_xlfn.DAYS(PlanTrabajo[[#This Row],[FECHA DE FIN]],PlanTrabajo[[#This Row],[FECHA DE INICIO]]))) -> 0
A24: CUMPLIMIENTO LEGAL | B24: COMITÉ DE CONVIVIENCIA LABORAL | C24: Capacitación al comite en funciones, responsabiidades, comunicación asertiva y resolución de conflictos | D24: Registro de capacitacion firmado por todos los integrantes del comité con evidencia de evaluación | J24: ='PLAN CAP'!#REF! -> #REF! | K24: =IF(G26=" "," ",(_xlfn.DAYS(PlanTrabajo[[#This Row],[FECHA DE FIN]],PlanTrabajo[[#This Row],[FECHA DE INICIO]]))) -> 0
A25: CUMPLIMIENTO LEGAL | B25: COMITÉ DE CONVIVIENCIA LABORAL | C25: Reunión trimestral del comité con evidencia de cumplimiento de sus funciones | D25: Acta de reunión trimetral donde se evidencien las activiades ejecutadas por el comité | J25: ='PLAN CAP'!#REF! -> #REF! | K25: =IF(G27=" "," ",(_xlfn.DAYS(PlanTrabajo[[#This Row],[FECHA DE FIN]],PlanTrabajo[[#This Row],[FECHA DE INICIO]]))) -> 0
A26: CUMPLIMIENTO LEGAL | B26: COMITÉ DE CONVIVIENCIA LABORAL | C26: Informe de gestión trimestral del comité a la gerencia | D26: Evidencia de informe trimestral presentado a la gerencia de gestión del comité con evidencia de firma de la gerencia y del comité | J26: ='PLAN CAP'!#REF! -> #REF! | K26: =IF(G28=" "," ",(_xlfn.DAYS(PlanTrabajo[[#This Row],[FECHA DE FIN]],PlanTrabajo[[#This Row],[FECHA DE INICIO]]))) -> 0
A27: FORMACION Y CAPACITACION | B27: INDUCCIÓN | C27: Realizaciòn de la inducción en seguridad a los trabajadores nuevos, que implica evaluación de la inducción. | D27: Registro de induccion firmado por el trabajador, evalución de la inducción calificada | J27: ='PLAN CAP'!#REF! -> #REF! | K27: =IF(G29=" "," ",(_xlfn.DAYS(PlanTrabajo[[#This Row],[FECHA DE FIN]],PlanTrabajo[[#This Row],[FECHA DE INICIO]]))) -> 0
... A61: CUMPLIMIENTO LEGAL | B61: PLAN DE PREVENCION, PREPARACIÓN Y RESPUESTA ANTE EMERGENCIAS | C61: Realizar simulacro de emergencia con entrega de guion de preparación de simulacro, e informe de simulacro | D61: Guia de preparación de simulacro, informe de simulacro | J61: ='PLAN CAP'!#REF! -> #REF! | K61: =IF(G63=" "," ",(_xlfn.DAYS(PlanTrabajo[[#This Row],[FECHA DE FIN]],PlanTrabajo[[#This Row],[FECHA DE INICIO]]))) -> 0
A62: GESTION DEL RIESGO | B62: QUIMICO | C62: Realizar la matriz de compatibilidad con con sistema globalmente armonizado | D62: Matriz de compatibilidad de sustancias quimicas divulgada y publicada | G62: 43132 | H62: 43189 | J62: ='PLAN CAP'!#REF! -> #REF! | K62: =IF(G64=" "," ",(_xlfn.DAYS(PlanTrabajo[[#This Row],[FECHA DE FIN]],PlanTrabajo[[#This Row],[FECHA DE INICIO]]))) -> 57
A63: GESTION DEL RIESGO | B63: QUIMICO | C63: Mantener las hojas de seguridad actualizadas y disponibles en el área de las sustancias que se manipulan o almacenan | D63: Hojas de segurirda de sustancias quimicas en un repositorio en las areas que se utilizan | G63: 43132 | H63: 43189 | J63: ='PLAN CAP'!#REF! -> #REF! | K63: =IF(G65=" "," ",(_xlfn.DAYS(PlanTrabajo[[#This Row],[FECHA DE FIN]],PlanTrabajo[[#This Row],[FECHA DE INICIO]]))) -> 57
A64: GESTION DEL RIESGO | B64: QUIMICO | C64: Mantener actualizado el inventario de sustancias quimicas y la matriz de compatibilidad | D64: Inventario de sustancias quimcias actualizado | G64: 43132 | H64: 43189 | J64: ='PLAN CAP'!#REF! -> #REF! | K64: =IF(G66=" "," ",(_xlfn.DAYS(PlanTrabajo[[#This Row],[FECHA DE FIN]],PlanTrabajo[[#This Row],[FECHA DE INICIO]]))) -> 57
A65: GESTION DEL RIESGO | B65: QUIMICO | C65: Procedmiento de manipulacion, almacenamiento, trasvase, transporte y disposicion final de productos quimicos | D65: Procedimiento de riesgo quimico | G65: 43132 | H65: 43189 | J65: ='PLAN CAP'!#REF! -> #REF! | K65: =IF(G67=" "," ",(_xlfn.DAYS(PlanTrabajo[[#This Row],[FECHA DE FIN]],PlanTrabajo[[#This Row],[FECHA DE INICIO]]))) -> 57
A66: GESTION DEL RIESGO | B66: QUIMICO | C66: Capacitar al personal en hojas de seguridad, matriz de compatibilidad y medidas de prevención como etiquetado, reenvase y almacenamiento. | D66: Registro de capacitación | G66: 43132 | H66: 43189 | J66: ='PLAN CAP'!#REF! -> #REF! | K66: =IF(G68=" "," ",(_xlfn.DAYS(PlanTrabajo[[#This Row],[FECHA DE FIN]],PlanTrabajo[[#This Row],[FECHA DE INICIO]]))) -> 57
A67: GESTION DEL RIESGO | B67: QUIMICO | C67: Realizar inspección de seguimiento para reenvase, rotulación y almacenamiento | D67: Registro de inspeccion | G67: 43132 | H67: 43189 | J67: ='PLAN CAP'!#REF! -> #REF! | K67: =IF(G69=" "," ",(_xlfn.DAYS(PlanTrabajo[[#This Row],[FECHA DE FIN]],PlanTrabajo[[#This Row],[FECHA DE INICIO]]))) -> 57
A68: GESTION DEL RIESGO | B68: ALTURAS | C68: Realizar el inventario de trabajo en alturas | D68: Inventario de tareas en alturas | G68: 43132 | H68: 43189 | J68: ='PLAN CAP'!#REF! -> #REF! | K68: =IF(G70=" "," ",(_xlfn.DAYS(PlanTrabajo[[#This Row],[FECHA DE FIN]],PlanTrabajo[[#This Row],[FECHA DE INICIO]]))) -> 57
A69: GESTION DEL RIESGO | B69: ALTURAS | C69: Control de personal expuesto a alturas mediente cuadro control de examens y cursos | D69: Cuadro control de personal expuesto a alturas | G69: 43132 | H69: 43189 | J69: ='PLAN CAP'!#REF! -> #REF! | K69: =IF(G71=" "," ",(_xlfn.DAYS(PlanTrabajo[[#This Row],[FECHA DE FIN]],PlanTrabajo[[#This Row],[FECHA DE INICIO]]))) -> 57
A70: GESTION DEL RIESGO | B70: ALTURAS | C70: Programar el personal a los cursos de alturas: Nivel Básico, Avanzado, Reentrenamiento y/o Coordinador, según aplique. | D70: Certificado de aptitud en alturas medico y certificado de curso de formación en alturas | G70: 43132 | H70: 43189 | J70: ='PLAN CAP'!#REF! -> #REF! | K70: =IF(G72=" "," ",(_xlfn.DAYS(PlanTrabajo[[#This Row],[FECHA DE FIN]],PlanTrabajo[[#This Row],[FECHA DE INICIO]]))) -> 57
A71: GESTION DEL RIESGO | B71: ALTURAS | C71: Construir hojas de vida de equipos de alturas | D71: Hojas de vida de equipos de alturas | G71: 43132 | H71: 43189 | J71: ='PLAN CAP'!#REF! -> #REF! | K71: =IF(G73=" "," ",(_xlfn.DAYS(PlanTrabajo[[#This Row],[FECHA DE FIN]],PlanTrabajo[[#This Row],[FECHA DE INICIO]]))) -> 57
A72: GESTION DEL RIESGO | B72: ALTURAS | C72: Mantener actualizado el inventario de equipos de alturas y hojas de vida de los equipos | D72: Inventario de equipos de alturas | G72: 43132 | H72: 43189 | J72: ='PLAN CAP'!#REF! -> #REF! | K72: =IF(G74=" "," ",(_xlfn.DAYS(PlanTrabajo[[#This Row],[FECHA DE FIN]],PlanTrabajo[[#This Row],[FECHA DE INICIO]]))) -> 57
A73: GESTION DEL RIESGO | B73: ALTURAS | C73: Realizar inspección validando la implementacion del programa de protección contra caidas: permiso de trabajo, epp, equipos de alturas. | D73: Registro de inspeccion de equipos de alturas por parte del coordinador en alturas | G73: 43132 | H73: 43189 | J73: ='PLAN CAP'!#REF! -> #REF! | K73: =IF(G75=" "," ",(_xlfn.DAYS(PlanTrabajo[[#This Row],[FECHA DE FIN]],PlanTrabajo[[#This Row],[FECHA DE INICIO]]))) -> 57
... A75: GESTION DEL RIESGO | B75: ALTURAS | C75: Realizar el permiso de trabajo en alturas y/o lista de chequeo y ATS previo a cada trabajo | D75: Permiso de trabajo o lista de cheque implementada. | G75: 43132 | H75: 43189 | J75: ='PLAN CAP'!#REF! -> #REF! | K75: =IF(G77=" "," ",(_xlfn.DAYS(PlanTrabajo[[#This Row],[FECHA DE FIN]],PlanTrabajo[[#This Row],[FECHA DE INICIO]]))) -> 57
A76: GESTION DEL RIESGO | B76: PROGRAMA DE MANTENIMIENTO | C76: Construir inventario de equipos, herramientas que tiene la erpresa | D76: Inventario de herramientas y equipos | J76: ='PLAN CAP'!#REF! -> #REF! | K76: =IF(G78=" "," ",(_xlfn.DAYS(PlanTrabajo[[#This Row],[FECHA DE FIN]],PlanTrabajo[[#This Row],[FECHA DE INICIO]]))) -> 0
A77: GESTION DEL RIESGO | B77: PROGRAMA DE MANTENIMIENTO | C77: Hacer la programación del mantenimiento de las herramientas y equipos | D77: Cronograma de mantenimeinto de herramientas y equipos | J77: ='PLAN CAP'!#REF! -> #REF! | K77: =IF(G79=" "," ",(_xlfn.DAYS(PlanTrabajo[[#This Row],[FECHA DE FIN]],PlanTrabajo[[#This Row],[FECHA DE INICIO]]))) -> 0
A78: GESTION DEL RIESGO | B78: PROGRAMA DE MANTENIMIENTO | C78: Construir hojas de vida de equipos y herramientas y registrar en ellas los mantenimientos realizados | D78: Hoja de vida actualizada con mantenimientos | J78: ='PLAN CAP'!#REF! -> #REF! | K78: =IF(G80=" "," ",(_xlfn.DAYS(PlanTrabajo[[#This Row],[FECHA DE FIN]],PlanTrabajo[[#This Row],[FECHA DE INICIO]]))) -> 0
A79: MEJORA CONTINUA | B79: RENDICIÓN DE CUENTAS | C79: Informe de rendición de cuentas del comité partitario, comité de convivencia, brigada de emergencias y coordinadores de seguridad del proyecto. | D79: Informe de rendicion de cuentas de comites, coordiandores a la gerencia | J79: ='PLAN CAP'!#REF! -> #REF! | K79: =IF(G81=" "," ",(_xlfn.DAYS(PlanTrabajo[[#This Row],[FECHA DE FIN]],PlanTrabajo[[#This Row],[FECHA DE INICIO]]))) -> 0
A80: GESTION DEL RIESGO | B80: AUDITIVO | C80: Realizar medición de ruido de acuerdo a la fuente de riesgo | D80: Informe de medición de ruido | G80: 43132 | H80: 43189 | J80: ='PLAN CAP'!#REF! -> #REF! | K80: =IF(G82=" "," ",(_xlfn.DAYS(PlanTrabajo[[#This Row],[FECHA DE FIN]],PlanTrabajo[[#This Row],[FECHA DE INICIO]]))) -> 57
A81: GESTION DEL RIESGO | B81: AUDITIVO | C81: Solicitar a la IPS el envio de resultado audimetrias a profesional de analisis | D81: Correo a IPS para que remita audiomterias a fonoaudiologa arl o medico | G81: 43132 | H81: 43189 | J81: ='PLAN CAP'!#REF! -> #REF! | K81: =IF(G83=" "," ",(_xlfn.DAYS(PlanTrabajo[[#This Row],[FECHA DE FIN]],PlanTrabajo[[#This Row],[FECHA DE INICIO]]))) -> 57
A82: GESTION DEL RIESGO | B82: AUDITIVO | C82: Tabulación de audiometrias periodicas vs ingreso para definir trabajadores con perdida auditiva | D82: Analisis de audiometrias cuadro de población objeto | G82: 43132 | H82: 43189 | J82: ='PLAN CAP'!#REF! -> #REF! | K82: =IF(G84=" "," ",(_xlfn.DAYS(PlanTrabajo[[#This Row],[FECHA DE FIN]],PlanTrabajo[[#This Row],[FECHA DE INICIO]]))) -> 57
A83: GESTION DEL RIESGO | B83: AUDITIVO | C83: Capacitar al personal en uso de protectores auditivos, mecanismos de prevención y cuidado del oido | D83: Registro de capaciación | G83: 43132 | H83: 43189 | J83: ='PLAN CAP'!#REF! -> #REF! | K83: =IF(G85=" "," ",(_xlfn.DAYS(PlanTrabajo[[#This Row],[FECHA DE FIN]],PlanTrabajo[[#This Row],[FECHA DE INICIO]]))) -> 57
A84: GESTION DEL RIESGO | B84: AUDITIVO | C84: Inspección de uso de elementos de proteccion auditiva | D84: Registro de isnpección en cuadro población objeto | G84: 43132 | H84: 43189 | J84: ='PLAN CAP'!#REF! -> #REF! | K84: =IF(G86=" "," ",(_xlfn.DAYS(PlanTrabajo[[#This Row],[FECHA DE FIN]],PlanTrabajo[[#This Row],[FECHA DE INICIO]]))) -> 57
A85: GESTION DEL RIESGO | B85: BIOMECANICO | C85: Caracterización del factor de riesgo biomecanico por puesto de trabajo | D85: Factor de riesgo ponderado por criticidad de riesgo biomecanico | G85: 43132 | H85: 43189 | J85: ='PLAN CAP'!#REF! -> #REF! | K85: =IF(G87=" "," ",(_xlfn.DAYS(PlanTrabajo[[#This Row],[FECHA DE FIN]],PlanTrabajo[[#This Row],[FECHA DE INICIO]]))) -> 57
A86: GESTION DEL RIESGO | B86: BIOMECANICO | C86: Análisis de población objeto del SVE con el cruce de informacion de exámenes medicos, ausentismo, accidentalidad, programa de reintegro laboral y la caracterizacion del riesgo por puesto de trabajo | D86: Poblacion objeto de auditivo | G86: 43132 | H86: 43189 | J86: ='PLAN CAP'!#REF! -> #REF! | K86: =IF(G88=" "," ",(_xlfn.DAYS(PlanTrabajo[[#This Row],[FECHA DE FIN]],PlanTrabajo[[#This Row],[FECHA DE INICIO]]))) -> 57
A87: GESTION DEL RIESGO | B87: BIOMECANICO | C87: Capacitación al personal en factor del riesgo biomecánico (higiene postural, pausas activas, levantamiento de cargas) | D87: registro de capacitacion | G87: 43132 | H87: 43189 | J87: ='PLAN CAP'!#REF! -> #REF! | K87: =IF(G89=" "," ",(_xlfn.DAYS(PlanTrabajo[[#This Row],[FECHA DE FIN]],PlanTrabajo[[#This Row],[FECHA DE INICIO]]))) -> 57
A88: GESTION DEL RIESGO | B88: BIOMECANICO | C88: Capacitación al personal en el programa de calistenia y pausas activas | D88: Registro de capaciación | G88: 43132 | H88: 43189 | J88: ='PLAN CAP'!#REF! -> #REF! | K88: =IF(G90=" "," ",(_xlfn.DAYS(PlanTrabajo[[#This Row],[FECHA DE FIN]],PlanTrabajo[[#This Row],[FECHA DE INICIO]]))) -> 57
A89: GESTION DEL RIESGO | B89: BIOMECANICO | C89: Documentación de procedimiento de riesgo biomecanico | D89: Programa documentado | J89: ='PLAN CAP'!#REF! -> #REF! | K89: =IF(G91=" "," ",(_xlfn.DAYS(PlanTrabajo[[#This Row],[FECHA DE FIN]],PlanTrabajo[[#This Row],[FECHA DE INICIO]]))) -> 0 | L89: Mayo 25 a las 6:30 a.m; Mayo 28 a la 1:00 p.m; Junio 2 a las 8:00 a.m
A90: GESTION DEL RIESGO | B90: PSICOSOCIAL | C90: Aplicación de la bateria de riesgo psicosocial | D90: Informe de diagnostico psicosocial | J90: ='PLAN CAP'!#REF! -> #REF! | K90: =IF(G92=" "," ",(_xlfn.DAYS(PlanTrabajo[[#This Row],[FECHA DE FIN]],PlanTrabajo[[#This Row],[FECHA DE INICIO]]))) -> 0
A91: GESTION DEL RIESGO | B91: PSICOSOCIAL | C91: Socializar el informe de diagnostico de factores psicosociales al comité de conviviencia | D91: Acta de comité con evidencia de socializacion de informe | J91: ='PLAN CAP'!#REF! -> #REF! | K91: =IF(G93=" "," ",(_xlfn.DAYS(PlanTrabajo[[#This Row],[FECHA DE FIN]],PlanTrabajo[[#This Row],[FECHA DE INICIO]]))) -> 0
A92: GESTION DEL RIESGO | B92: PSICOSOCIAL | C92: Socializar el informe de diagnostico de factores psicosociales con la Gerencia. | D92: Aprobación de plan de trabajo | J92: ='PLAN CAP'!#REF! -> #REF! | K92: =IF(G94=" "," ",(_xlfn.DAYS(PlanTrabajo[[#This Row],[FECHA DE FIN]],PlanTrabajo[[#This Row],[FECHA DE INICIO]]))) -> 0
A93: GESTION DEL RIESGO | B93: PSICOSOCIAL | C93: Establecer plan de trabajo de acuerdo al diagnostico | D93: Programa psicosocial ajustado | J93: ='PLAN CAP'!#REF! -> #REF! | K93: =IF(G95=" "," ",(_xlfn.DAYS(PlanTrabajo[[#This Row],[FECHA DE FIN]],PlanTrabajo[[#This Row],[FECHA DE INICIO]]))) -> 0 | L93: PORCENTAJE DE EJECUCIÓN DE ACTIVIDADES PLANEADAS
J94: ='PLAN CAP'!#REF! -> #REF! | K94: =IF(G96=" "," ",(_xlfn.DAYS(PlanTrabajo[[#This Row],[FECHA DE FIN]],PlanTrabajo[[#This Row],[FECHA DE INICIO]]))) -> 0
J95: ='PLAN CAP'!#REF! -> #REF! | K95: =IF(G97=" "," ",(_xlfn.DAYS(PlanTrabajo[[#This Row],[FECHA DE FIN]],PlanTrabajo[[#This Row],[FECHA DE INICIO]]))) -> 0
J96: ='PLAN CAP'!#REF! -> #REF! | K96: =IF(G98=" "," ",(_xlfn.DAYS(PlanTrabajo[[#This Row],[FECHA DE FIN]],PlanTrabajo[[#This Row],[FECHA DE INICIO]]))) -> 0
J97: ='PLAN CAP'!#REF! -> #REF! | K97: =IF(G99=" "," ",(_xlfn.DAYS(PlanTrabajo[[#This Row],[FECHA DE FIN]],PlanTrabajo[[#This Row],[FECHA DE INICIO]]))) -> 0
J98: ='PLAN CAP'!#REF! -> #REF! | K98: =IF(G100=" "," ",(_xlfn.DAYS(PlanTrabajo[[#This Row],[FECHA DE FIN]],PlanTrabajo[[#This Row],[FECHA DE INICIO]]))) -> 0
J99: ='PLAN CAP'!#REF! -> #REF! | K99: =IF(G101=" "," ",(_xlfn.DAYS(PlanTrabajo[[#This Row],[FECHA DE FIN]],PlanTrabajo[[#This Row],[FECHA DE INICIO]]))) -> 0
J100: ='PLAN CAP'!#REF! -> #REF! | K100: =IF(G102=" "," ",(_xlfn.DAYS(PlanTrabajo[[#This Row],[FECHA DE FIN]],PlanTrabajo[[#This Row],[FECHA DE INICIO]]))) -> 0
J101: ='PLAN CAP'!#REF! -> #REF! | K101: =IF(G103=" "," ",(_xlfn.DAYS(PlanTrabajo[[#This Row],[FECHA DE FIN]],PlanTrabajo[[#This Row],[FECHA DE INICIO]]))) -> 0
J102: ='PLAN CAP'!#REF! -> #REF! | K102: =IF(G104=" "," ",(_xlfn.DAYS(PlanTrabajo[[#This Row],[FECHA DE FIN]],PlanTrabajo[[#This Row],[FECHA DE INICIO]]))) -> 0
J103: ='PLAN CAP'!#REF! -> #REF! | K103: =IF(G105=" "," ",(_xlfn.DAYS(PlanTrabajo[[#This Row],[FECHA DE FIN]],PlanTrabajo[[#This Row],[FECHA DE INICIO]]))) -> 0
J104: ='PLAN CAP'!#REF! -> #REF! | K104: =IF(G106=" "," ",(_xlfn.DAYS(PlanTrabajo[[#This Row],[FECHA DE FIN]],PlanTrabajo[[#This Row],[FECHA DE INICIO]]))) -> 0
J105: ='PLAN CAP'!#REF! -> #REF! | K105: =IF(G107=" "," ",(_xlfn.DAYS(PlanTrabajo[[#This Row],[FECHA DE FIN]],PlanTrabajo[[#This Row],[FECHA DE INICIO]]))) -> 0
... J499: ='PLAN CAP'!#REF! -> #REF! | K499: =IF(G501=" "," ",(_xlfn.DAYS(PlanTrabajo[[#This Row],[FECHA DE FIN]],PlanTrabajo[[#This Row],[FECHA DE INICIO]]))) -> 0

Sheet VALD
B1: 43101 | I1: MESES | K1: AVANCE ACTIVIDADES
B2: 43465 | I2: ENERO | K2: 0 | N2: ACTIVIDADES
I3: FEBRERO | K3: 0.25 | N3: PLANEADA | O3: 1
I4: MARZO | K4: 0.5 | N4: EJECUTADA | O4: 2
I5: ABRIL | K5: 0.75 | N5: CANCELADA | O5: 0
I6: MAYO | K6: 1 | N6: REPROGRAMADA | O6: 0
I7: JUNIO
I8: JULIO
I9: AGOSTO
I10: SEPTIEMBRE
I11: OCTUBRE
I12: NOVIEMBRE
I13: DICIEMBRE
I14: ENERO
I15: FEBRERO
I16: MARZO
I17: ABRIL
I18: MAYO
... I25: DICIEMBRE

Sheet VALID_2
B4: Etiquetas de fila | C4: Promedio de % COMPLETADO
B5: MATRIZ DE PELIGROS | C5: 0
B6: PLAN DE EMERGENCIAS | C6: 0
B7: RIESGO SOCIOPOLITICO | C7: 0
B8: RIESGO BIOLOGICO | C8: 0
B9: CALIDAD | C9: 0
B10: PROMOCION Y PREVENCIÓN | C10: 0
B11: PROGRAMA DE GESTIÓN PARA EL RIESGO ELÉCTRICO | C11: 0
B12: PROGRAMA DE RIESGO PSICOSOCIAL | C12: 0
B13: PROGRAMA ESTILOS DE VIDA SALUDABLE | C13: 0
B14: PROGRAMA DE GESTIÓN DE RIESGO QUIMICO2 | C14: 0
B15: RIESGO MECANICO | C15: 0
B16: PROGRAMA DE GESTION DE RIESGO RUIDO | C16: 0
... B27: Total general | C27: 0
E41: RESPONSABLES | F41: OBJETIVO DE LA ACTIVIDAD
B42: FACTOR DE RIESGO/PROGRAMA | E42: COORDINADOR HSEQ | F42: INTERVENCION DEL RIESGO
B43: MATRIZ DE PELIGROS | E43: LIDER AMBIENTAL/FORESTAL | F43: PARTICIPACION Y CONSULTA
B44: INDUCCION / REINDUCCION SGI | E44: ARL SURA/COORDINADOR HSEQ | F44: PLAN DE EMERGENCIAS
B45: RIESGO SOCIOPOLITICO | E45: COODINADOR HSEQ | F45: PROCESO DE INDUCCION / REINDUCCIÒN
B46: RIESGO BIOLOGICO | F46: PROTECCION DE MEDIO AMBIENTE
B47: GESTION AMBIENTAL/FORESTAL | F47: SATISFACCION DEL CLIENTE
B48: GESTION AMBIENTAL/PROGRAMA DE ENERGIAS LIMPIAS | F48: INTERVENCIÒN DEL RIESGO / PLAN DE EMERGENCIAS
B49: GESTION AMBIENTAL/PROGRAMA DE GESTION INTEGRAL DE RESIDUOS | F49: ISO 900:2015
B50: CALIDAD
B51: PLAN ESTRATEGICO DE SEGURIDAD VIAL
B52: PROMOCION Y PREVENCIÓN
B53: CONDICIONES DE SEGURIDAD/INSPECCIONES
B54: PROGRAMA DE GESTIÓN PARA EL RIESGO ELÉCTRICO
B55: PROGRAMA DE RIESGO PSICOSOCIAL
B56: PROGRAMA ESTILOS DE VIDA SALUDABLE
B57: PROGRAMA DE SVE OSTEOMUSCULAR
B58: PROGRAMA DE GESTIÓN DE RIESGO QUIMICO
B59: PROGRAMA DE GESTIÓN PARA EL RIESGO ELÉCTRICO/ PROGRAMA DE GESTIÒN DEL RIESGO CONTRA CAIDAS
B60: RIESGO MECANICO
B61: PROGRAMA DE GESTIÓN PARA EL RIESGO ELÉCTRICO / PLAN DE EMERGENCIAS
... B94: se requiere documento con capacitacion que incluya tema: xxx para personal de sector electrico y contrucción que incluya objetivos relacionados a: Capacitar y fortalecer conocimientos al personal en:
